Workbook

Sheet checkout
A1: Test Case ID | B1: Group | C1: Module | D1: Feature | E1: Test Level | F1: Test Type | G1: Priority | H1: Script Status | I1: Automatable | J1: Assignee | K1: Script File / Notes | L1: Preconditions | M1: Test Data | N1: Test Steps | O1: Expected Result | P1: Code Evidence | Q1: Remark
A2: TC-HOME-01-R | B2: Home / Navigation | C2: Home | D2: เมนูหมวด | E2: UI | F2: Positive | G2: High | H2: Script Done | I2: Yes | K2: tests/checkout/TC-HOME-01-R_category-menu-navigates.robot — PASS (RF port) | L2: Home โหลดสำเร็จ | M2: เมนู "พวงหรีดดอกไม้สด" | N2: 1.เปิด `/` 2.คลิก dropdown 3.คลิกหมวดย่อย | O2: URL เปลี่ยนเป็น slug หมวด, listing แสดงสินค้าหมวดนั้น, breadcrumb ตรง | P2: `src/app/[...slug]/page.tsx` | Q2: เมนูหลัก `href="#"`+JS
A3: TC-HOME-02 | B3: Home / Navigation | C3: Home | D3: แบนเนอร์/โซเชียล | E3: Manual Exploratory | F3: Positive | G3: Low | H3: Not Started | L3: Home โหลดสำเร็จ | M3: แบนเนอร์ขายดี, LINE, tel | N3: 1.คลิกแบนเนอร์ 2.คลิก LINE/โทร | O3: แบนเนอร์ → collection ถูก; LINE/โทร deep link | P3: `home/*`, `Footer` | Q3: external — assert URL
A4: TC-CAT-01-R | B4: Category / Listing / Search | C4: Category | D4: แสดงสินค้า | E4: UI | F4: Positive | G4: High | H4: Script Done | I4: Yes | K4: tests/category/TC-CAT-01_listing-renders.robot — PASS (RF; robot tag TC-CAT-01) | L4: มีสินค้าในหมวด | M4: `/ร้านพวงหรีด/พวงหรีดดอกไม้สด/` | N4: 1.เปิดหมวด 2.ตรวจการ์ด | O4: แสดงรูป/ชื่อ/รหัส/ราคาโปร+เดิม, จำนวนรวมถูก | P4: `app/products/page.tsx` | Q4: smoke
A5: TC-CAT-02-R | B5: Category / Listing / Search | C5: Category | D5: Sort | E5: UI | F5: Positive/Boundary | G5: High | H5: Not Started | L5: listing ≥2 สินค้า | M5: sort: แนะนำ/ช่วงราคา | N5: 1.เลือก sort 2.อ่าน URL param 3.parse ราคา | O5: "ช่วงราคา"→param `price` เรียงถูก; "แนะนำ"→`recommend`; URL คงค่า | P5: `filter.ts:41-42` | Q5: data-driven
A6: TC-CAT-03 | B6: Category / Listing / Search | C6: Category | D6: Filter + ล้าง | E6: UI | F6: Positive | G6: High | H6: Not Started | L6: อยู่ listing | M6: ตัวกรองช่วงราคา/ประเภท | N6: 1.เลือกตัวกรอง 2.ตรวจผล 3.ล้างตัวกรอง | O6: ผลตรงเงื่อนไข; ล้าง→รายการเต็ม; ตัวนับอัปเดต | P6: `filter.ts`, `process_*_condition` | Q6: keep
A7: TC-CAT-04 | B7: Category / Listing / Search | C7: Category | D7: Pagination | E7: UI | F7: Boundary | G7: Medium | H7: Not Started | L7: หมวดหลายหน้า | M7: หน้า 1/2/สุดท้าย | N7: 1.คลิกถัดไป/เลขหน้า 2.หน้าสุดท้าย 3.ก่อนหน้า | O7: เปลี่ยนหน้าถูก; ก่อนหน้า disabled ที่หน้า1; ไม่ซ้ำข้ามหน้า | P7: `Pagination.tsx`, `_products` paginate | Q7: ยืนยัน page vs load-more
A8: TC-CAT-05-R | B8: Category / Listing / Search | C8: Category | D8: Empty result | E8: UI | F8: Negative | G8: Medium | H8: Not Started | L8: — | M8: filter combo ที่ให้ 0 ผล | N8: 1.ตั้งตัวกรองเข้มจน 0 รายการ | O8: empty state สื่อความหมาย + ทางเลือกล้างตัวกรอง | P8: `ProductSection` (empty) | Q8: ระบุ filter combo
A9: TC-CAT-06 | B9: Category / Listing / Search | C9: Category | D9: EXCLUDED_TAGS | E9: UI | F9: Negative | G9: Medium | H9: Not Started | L9: — | M9: หมวดที่มี excluded tag | N9: 1.เปิด listing | O9: สินค้า excluded ไม่แสดง | P9: `StoreController::process_excluded_tags` | Q9: ขอค่า env
A10: TC-SRCH-01-R | B10: Category / Listing / Search | C10: Search | D10: keyword vs UI box | E10: UI | F10: Negative/Exploratory | G10: Medium | H10: Not Started | L10: — | M10: keyword="ดอกไม้สด" | N10: 1.หา search box (UI) 2.เปิด listing `?keyword=` | O10: **BE รองรับ `?keyword=` (listing กรองได้)**; กล่อง UI = `Not verifiable from code` | P10: `app/products/page.tsx:62-68` | Q10: แก้ assumption DEF-001
A11: TC-PDP-01-R | B11: Product Detail | C11: PDP | D11: แสดงข้อมูล | E11: UI | F11: Positive | G11: High | H11: Script Done | I11: Yes | K11: tests/product/TC-PDP-01_detail-info.robot — PASS (RF, data-driven; robot tag TC-PDP-01) | L11: สินค้ามีอยู่ | M11: `/พวงหรีด/<slug>/` | N11: 1.เปิด PDP 2.ตรวจชื่อ/รหัส/ราคา/ไซซ์/breadcrumb | O11: ข้อมูลตรง listing; ราคาโปร+เดิม; breadcrumb ถูก | P11: `api/product:getProductBySlug` | Q11: parameterize ต่อหลาย slug
A12: TC-PDP-02 | B12: Product Detail | C12: PDP | D12: Add to Cart | E12: UI | F12: Positive | G12: High | H12: Script Done | I12: Yes | K12: tests/product/TC-PDP-04_add-to-cart-badge.robot — PASS (RF; robot tag TC-PDP-04) | L12: ตะกร้าว่าง | M12: TD-03 | N12: 1.กด "เพิ่มลงตะกร้า" 2.ดูตัวนับ 3.เปิด /cart/ | O12: ตัวนับ +1; สินค้า+ราคาถูกใน cart; toast | P12: `AddItemButton`, `cart.ts` | Q12: critical
A13: TC-PDP-03-R | B13: Product Detail | C13: PDP | D13: Buy Now | E13: UI | F13: Positive | G13: High | H13: Script Done | I13: Yes | K13: tests/checkout/TC-PDP-03-R_buy-now-checkout.robot — PASS (Buy Now + sessionStorage, RF) | L13: TD-03 `allow_add_to_cart=true` | M13: H015 | N13: 1.กด "ซื้อทันที!" | O13: set `sessionStorage['checkoutProduct']`=สินค้านี้ → ไป `/checkout` ตรง (ข้าม cart) | P13: `ProductButton:88-102` | Q13: ต่างจาก add-to-cart
A14: TC-PDP-05 | B14: Product Detail | C14: PDP | D14: สั่งไม่ได้ | E14: UI | F14: Negative | G14: Medium | H14: Not Started | L14: TD-04 | M14: — | N14: 1.เปิด PDP สินค้าสั่งไม่ได้ | O14: ซ่อนปุ่ม Buy Now, แสดงลิงก์ LINE | P14: `ProductButton:131-150` | Q14: —
A15: TC-CART-01 | B15: Cart | C15: Cart | D15: Empty state | E15: UI | F15: Negative | G15: Medium | H15: Script Done | I15: Yes | K15: tests/checkout/TC-CART-01_empty-cart-message.robot — PASS (empty-state, RF) | L15: ตะกร้าว่าง | M15: — | N15: 1.เปิด `/cart/` | O15: "- คุณยังไม่มีสินค้าในตะกร้า -"; ยอด ฿0 | P15: `cart/page.tsx`, `CartItem` | Q15: ปุ่มชำระ disable = ยืนยัน
A16: TC-CART-02-R | B16: Cart | C16: Cart | D16: เพิ่ม/ลดจำนวน | E16: UI | F16: Positive | G16: High | H16: Script Done | I16: Yes | K16: tests/cart/TC-CART-02-R_qty-updates-total.robot — PASS (RF) | L16: ≥1 สินค้าในตะกร้า | M16: qty 1→2→1 | N16: 1.กด + 2.กด − 3.ดูยอดรวม | O16: ยอด = qty×ราคา; อัปเดตทุกครั้ง | P16: `AddItemButton:39-92` | Q16: —
A17: TC-CART-02b-R | B17: Cart | C17: Cart | D17: ลดถึง 0 → ลบ | E17: UI | F17: Boundary | G17: Medium | H17: Script Done | I17: Yes | K17: tests/cart/TC-CART-02b-R_last-unit-removed.robot — PASS (reduce to 0 → removed, RF) | L17: มี 1 สินค้า qty=1 | M17: — | N17: 1.กด − ตอน qty=1 | O17: ลบสินค้า + toast "ลบสินค้าออกจากตะกร้า" | P17: `AddItemButton:69-81` | Q17: —
A18: TC-CART-03-R | B18: Cart | C18: Cart | D18: persist (guest) | E18: UI | F18: Regression | G18: Medium | H18: Not Started | L18: guest, มีสินค้า | M18: — | N18: 1.เพิ่มสินค้า 2.refresh | O18: คงอยู่ใน `localStorage['cart']` | P18: `storage.ts:71-84` | Q18: —
A19: TC-CART-04 | B19: Cart | C19: Cart | D19: ไป Checkout | E19: UI | F19: Positive | G19: High | H19: Script Done | I19: Yes | K19: tests/cart/TC-CART-03_proceed-to-checkout.robot — PASS (RF; robot tag TC-CART-03) | L19: มีสินค้า (กทม.) | M19: — | N19: 1.กดปุ่มไปชำระเงิน | O19: ไป `/checkout` พร้อมสรุปยอด | P19: `ProductButton:88-102` | Q19: critical
A20: TC-CART-05-R | B20: Cart | C20: Checkout | D20: ต่างจังหวัด → LINE | E20: UI | F20: Negative | G20: Medium | H20: Not Started | L20: มีสินค้า, อยู่ checkout | M20: TD-15 | N20: 1.เลือกวัดนอก 6 จังหวัด | O20: disable ปุ่มชำระ + modal นำไป LINE | P20: `CheckoutForm:onChangeWat:248` | Q20: แก้ trigger ให้ตรง flow
A21: TC-CART-06 | B21: Cart | C21: Cart | D21: เกิน 10 ชิ้น | E21: UI | F21: Boundary | G21: High | H21: Script Done | I21: Yes | K21: tests/cart/TC-CART-06_qty-capped-at-10.robot — PASS (cap at 10, RF) | L21: ตะกร้ามี 10 | M21: TD-06 | N21: 1.กด + จนรวม 11 | O21: แสดง modal, จำกัดไม่เกิน 10 | P21: `AddItemButton:46-52` | Q21: boundary 10/11
A22: TC-CART-07 | B22: Cart | C22: Cart | D22: guest→login sync | E22: Integration | F22: Positive | G22: Medium | H22: Not Started | L22: guest มีของในตะกร้า | M22: TD-01→TD-02 | N22: 1.เพิ่มของ (guest) 2.login | O22: cart merge ไม่หาย (`synUserCart`) | P22: `cart.ts:25-48` | Q22: —
A23: TC-CHK-01-R | B23: Checkout (Validation + Shipping + Message Card) | C23: Checkout | D23: Happy path เต็ม | E23: Integration | F23: Positive | G23: High | H23: Script Done | I23: Yes | K23: tests/e2e/TC-PAY_full-purchase-loop.robot — happy path เต็ม → /payment (RF). @createsorder: gated, skip บน PROD ถ้าไม่ตั้ง ALLOW_PROD_ORDER; บน staging สร้าง order จริง | L23: มีสินค้า, **message card ครบ** | M23: วัด+วันที่(อนาคต ≥4ชม)+เวลา slot+ผู้สั่ง+email+phone `08xxxxxxxx`+consent+ribbon | N23: 1.กรอกครบ+ribbon 2.เลือกชำระ 3.กดชำระ | O23: ผ่าน → redirect `/payment/{tracking_id}` (หยุดก่อนชำระจริง) | P23: `onCreateOrder`, `OrderController:store` | Q23: critical; param payment method
A24: TC-CHK-02-R | B24: Checkout (Validation + Shipping + Message Card) | C24: Checkout | D24: required ว่าง | E24: UI | F24: Validation | G24: High | H24: Not Started | L24: กรอกเกือบครบ | M24: param: wat, delivery_date, delivery_time, deceased/ศาลา/เบอร์, ผู้สั่ง, email, phone, ribbon | N24: 1.เว้นทีละช่อง 2.กดชำระ | O24: block submit + error ใต้ช่อง | P24: `validation/checkout.ts`, `getValidationErrors` | Q24: parameterize
A25: TC-CHK-03 | B25: Checkout (Validation + Shipping + Message Card) | C25: Checkout | D25: email | E25: UI | F25: Validation | G25: High | H25: Not Started | L25: อยู่ checkout | M25: valid:`a@b.com`,`a.b+c@sub.co.th` / invalid:`abc`,`abc@`,`@x.com` | N25: 1.กรอกอีเมล 2.blur/submit | O25: invalid reject; valid ผ่าน | P25: `validation/checkout.ts` yup `.email()` | Q25: parameterize
A26: TC-CHK-04-UI | B26: Checkout (Validation + Shipping + Message Card) | C26: Checkout | D26: phone (FE) | E26: UI | F26: Validation | G26: High | H26: Not Started | L26: อยู่ checkout | M26: `0812345678`(ผ่าน), `+66...`(reject) | N26: 1.กรอก 2.blur/submit | O26: FE: เฉพาะ `^0\d{9}$` ผ่าน | P26: `validation/checkout.ts:customer_phone_number` | Q26: คู่กับ -API
A27: TC-CHK-04-API | B27: Checkout (Validation + Shipping + Message Card) | C27: Checkout | D27: phone (BE) | E27: API | F27: FE/BE Inconsistency | G27: High | H27: Not Started | L27: — | M27: `+66812345678`, `02xxxxxxx` | N27: 1.POST `/api/order` ตรง | O27: **BE รับ +66/เบอร์บ้าน** (regex กว้างกว่า FE) → inconsistency | P27: `OrderController:store:customer.phone_number` | Q27: risk RSK-02
A28: TC-CHK-05-UI | B28: Checkout (Validation + Shipping + Message Card) | C28: Checkout | D28: consent (FE) | E28: UI | F28: Negative | G28: High | H28: Script Done | I28: Yes | K28: tests/checkout/TC-CHK-05-UI_consent-gate.robot — DEFECT RSK-01/TC-SEC-01: Skip until consent enforced (RF) | L28: กรอกครบ ไม่ติ๊ก consent | M28: — | N28: 1.ไม่ติ๊ก 2.กดชำระ | O28: FE block + แจ้งยอมรับนโยบาย | P28: `privacy_policy_accepted` (yup) | Q28: คู่กับ SEC-01
A29: TC-CHK-06-R | B29: Checkout (Validation + Shipping + Message Card) | C29: Checkout | D29: คำนวณยอด | E29: Integration | F29: Positive | H29: Not Started | L29: 2-3 สินค้า, login (ถ้าใช้คูปอง) | M29: สินค้าราคาต่าง + coupon | N29: 1.ดู subtotal 2.ค่าส่ง 3.coupon 4.grand total | O29: ยอดจาก `/order/total-payment`: total=(สินค้า+ส่ง−ลด); กทม.ส่งฟรี | P29: `get_total_payment:~1610` | Q29: —
A30: TC-CHK-08-R | B30: Checkout (Validation + Shipping + Message Card) | C30: Checkout | D30: boundary ข้อความ | E30: UI/API | F30: Boundary | G30: Medium | H30: Not Started | L30: อยู่ checkout | M30: "ก"×255 / ×256 / emoji / เว้นหน้า-หลัง | N30: 1.กรอกศาลา/ป้าย 2.submit | O30: ≤255 ผ่าน; >255 reject "ยาวได้สูงสุด 255"; trim | P30: `OrderController:store` max:255 | Q30: parameterize
A31: TC-PDP-04-R | B31: Checkout (Validation + Shipping + Message Card) | C31: Checkout | D31: ข้อความริบบิ้น (มีจริง) | E31: UI | F31: Validation | G31: High | H31: Script Done | I31: Yes | K31: tests/checkout/TC-PDP-04-R_ribbon-persists.robot — PASS (ribbon @checkout, DEF-003 closed, RF) | L31: มีสินค้า, อยู่ /checkout | M31: "ด้วยรักและอาลัย" | N31: 1.เปิด MessageCard modal 2.กรอก attachedMessage1 3.บันทึก | O31: ช่องริบบิ้น **มีจริงที่ Checkout**; เก็บ `localStorage['messageCardModal-{n}-{code}']`; ส่งเป็น `attached_message_1` | P31: `MessageCardModal`, `validateMessageCards:38` | Q31: **ปิด DEF-003 (assumption ผิด)**
A32: TC-CHK-09 | B32: Checkout (Validation + Shipping + Message Card) | C32: Checkout | D32: delivery อดีต | E32: API/UI | F32: Negative | G32: High | H32: Script Done | I32: Yes | K32: tests/checkout_rules/TC-CHK-09_delivery-past-rejected.robot — PASS | L32: มีสินค้า, เลือกวัด | M32: delivery_date=เมื่อวาน, time=12:00 | N32: 1.กรอกวัน-เวลาอดีต 2.กดชำระ/POST order | O32: reject "ไม่สามารถย้อนเวลาไปส่งให้ในอดีตได้..." | P32: `Rules/PossibleDeliveryDateTime.php:22-26` | Q32: —
A33: TC-CHK-10 | B33: Checkout (Validation + Shipping + Message Card) | C33: Checkout | D33: delivery < 4 ชม. | E33: API/UI | F33: Boundary | G33: High | H33: Blocked | I33: Partial | K33: ขึ้นกับเวลาปัจจุบัน (time slot <4ชม.) → flaky, รอ mock เวลา | L33: มีสินค้า, เลือกวัด | M33: now+3ชม(fail)/now+4ชม(pass) | N33: 1.เลือกเวลาใกล้ 2.submit | O33: <4ชม reject "...ภายใน 4 ชั่วโมง..."; =4ชม ผ่าน | P33: `PossibleDeliveryDateTime.php:29-35` | Q33: parameterize
A34: TC-CHK-11 | B34: Checkout (Validation + Shipping + Message Card) | C34: Checkout | D34: delivery > 30 วัน | E34: API | F34: Boundary | G34: Medium | H34: Script Done | I34: Yes | K34: tests/checkout_rules/TC-CHK-11_delivery-over-30days-rejected.robot — PASS (+30 ได้ / +31 ไม่ได้) | L34: มีสินค้า | M34: now+30วัน(pass)/now+31วัน(fail) | N34: 1.เลือกวันไกล 2.submit | O34: >30วัน reject "...เกิน 30 วัน" | P34: `PossibleDeliveryDateTime.php:38-44` | Q34: parameterize
A35: TC-CHK-12 | B35: Checkout (Validation + Shipping + Message Card) | C35: Checkout | D35: slug ไม่มีจริง | E35: API | F35: API Error | G35: High | H35: Blocked | I35: Partial | K35: API-level: POST /api/order payload — รอเปิด RequestsLibrary | L35: — | M35: TD-05 | N35: 1.แก้ payload/sessionStorage 2.POST `/api/order` | O35: reject "ไม่พบสินค้าตาม slug ... ในตะกร้า" | P35: `Rules/ProductSlugExists.php:20-31` | Q35: —
A36: TC-CHK-13 | B36: Checkout (Validation + Shipping + Message Card) | C36: Checkout | D36: ป้ายน้อยกว่าจำนวน | E36: API/UI | F36: Validation | G36: High | H36: Script Done | I36: Yes | K36: tests/checkout_rules/TC-CHK-13_message-card-count.robot — PASS | L36: สินค้า amount=2 | M36: กรอก message card 1 ใบ | N36: 1.เพิ่ม 2 ชิ้น 2.กรอกป้าย 1 3.กดชำระ | O36: reject "...จำนวน 2 ชิ้น แต่ระบุข้อความ ... 1" | P36: `OrderController:store` cart.* closure | Q36: —
A37: TC-SHIP-01 | B37: Checkout (Validation + Shipping + Message Card) | C37: Shipping | D37: allow_delivery=false | E37: Integration | F37: Negative | H37: Not Started | L37: — | M37: TD-16 | N37: 1.เลือกวัดนั้น | O37: modal "...ติดต่อทีมบริการลูกค้า @wreathmala" | P37: `fetchDeliveryFee:~340` | Q37: ขอ location จาก dev
A38: TC-EMPTY-01 | B38: Checkout (Validation + Shipping + Message Card) | C38: Checkout | D38: /checkout ไม่มีสินค้า | E38: UI | F38: Empty State | G38: Medium | H38: Script Done | I38: Yes | K38: tests/checkout/TC-EMPTY-01_checkout-empty-cart.robot — PASS (RF) | L38: ตะกร้าว่าง | M38: — | N38: 1.เข้า `/checkout` ตรง | O38: จัดการ `'{}'` fallback, ไม่ crash | P38: `contexts/checkout:getProductPayload` | Q38: —
A39: TC-LOAD-01 | B39: Checkout (Validation + Shipping + Message Card) | C39: Checkout | D39: double submit | E39: UI | F39: Race Condition | G39: High | H39: Not Started | L39: กรอกครบ | M39: — | N39: 1.กดชำระเงินรัว ๆ 2 ครั้ง | O39: `isSubmitting` block ครั้งที่ 2, ไม่สร้างออเดอร์ซ้ำ | P39: `CheckoutForm:onSubmit`, `disableButton` | Q39: —
A40: TC-PROMO-01-R | B40: Coupon / Promotion | C40: Promotion | D40: คูปองถูกต้อง | E40: Integration | F40: Positive | G40: High | H40: Blocked | I40: Yes | K40: รอ valid code ที่ loginUser ยังไม่เคยใช้ (QA-Coupon-TestData-Request.md §1.1) | L40: **login (web_user_token)**, สินค้าในเขต, ยอดในช่วง min/max | M40: TD-07 | N40: 1.login 2.checkout 3.กรอกคูปอง 4.Apply | O40: `_infos.error=false`, ส่วนลดถูกหัก, grand total ลด | P40: `validate_coupon:1356` | Q40: ต้อง login
A41: TC-PROMO-02-R | B41: Coupon / Promotion | C41: Promotion | D41: คูปองผิด | E41: Integration | F41: Negative | G41: High | H41: Script Done | I41: Yes | K41: tests/promo/TC-PROMO-02-R_invalid-expired-coupon.robot — invalid PASS; expired(WD12) Skipped รอ codeExpired จริง | L41: login, checkout | M41: param: ไม่พบ/used/ยอด<min/ยอด>max | N41: 1.กรอกแต่ละโค้ด 2.Apply | O41: error ตรงกรณีจริง (ไม่พบ/WM21/used) | P41: `validate_coupon`, `Controller.php:917-934` | Q41: parameterize
A42: TC-PROMO-03-R | B42: Coupon / Promotion | C42: Promotion | D42: uppercase/ว่าง | E42: Integration | F42: Validation | G42: Medium | H42: Script Done | I42: Yes | K42: tests/promo/TC-PROMO-03-R_empty-coupon-code.robot — empty PASS; sub-case lowercase รอ valid code | L42: login, checkout | M42: "abc123"(จริง ABC123), "" | N42: 1.กรอก 2.Apply | O42: พิมพ์เล็กใช้ได้ (strtoupper); ว่าง→"กรุณากรอกรหัสส่วนลด" | P42: `validate_coupon:1369,1360` | Q42: —
A43: TC-PROMO-04 | B43: Coupon / Promotion | C43: Promotion | D43: guest ใส่คูปอง | E43: Integration | F43: Permission | G43: High | H43: Script Done | I43: Yes | K43: tests/promo/TC-PROMO-04_guest-coupon-requires-login.robot — PASS | L43: **ไม่ login** | M43: TD-01 + coupon valid | N43: 1.checkout (guest) 2.กรอกคูปอง 3.Apply | O43: "ต้องล๊อคอินเข้าสู่ระบบก่อนค่ะ" | P43: `validate_coupon:1416-1424` | Q43: —
A44: TC-PROMO-05 | B44: Coupon / Promotion | C44: Promotion | D44: ยอด < discount_min | E44: API | F44: Negative | G44: High | H44: Blocked | I44: Yes | K44: ยอด<min ทำไม่ได้ (สินค้าถูกสุด ~1,599 > min 1,000) — รอ data | L44: login, TD-10 | M44: ยอด < min | N44: 1.Apply คูปอง | O44: WM21 "ราคารวม...ไม่สามารถประยุกต์ใช้..." | P44: `Controller.php:917-934` | Q44: —
A45: TC-PROMO-06 | B45: Coupon / Promotion | C45: Promotion | D45: ยอดพอดี min/max | E45: API | F45: Boundary | G45: Medium | H45: Blocked | I45: Yes | K45: boundary min/max — รอ data + จัดยอดให้เข้าเงื่อนไข | L45: login, TD-10 | M45: ยอด=min, =max | N45: 1.Apply | O45: ค่าขอบพอดี **ใช้ไม่ได้** (`>min && <max`) | P45: `Controller.php:918` | Q45: strict boundary
A46: TC-PROMO-07 | B46: Coupon / Promotion | C46: Promotion | D46: คูปองใช้ซ้ำ | E46: Integration | F46: Negative | G46: High | H46: Script Done | I46: Yes | K46: tests/promo/TC-PROMO-07_used-coupon-rejected.robot — PASS (DISCOUNT10) | L46: login + เคยใช้ (TD-09) | M46: coupon used | N46: 1.Apply คูปองเดิม | O46: "ท่านได้ใช้รหัสส่วนลด ... ไปแล้วค่ะ" | P46: `validate_coupon:1426-1438` | Q46: —
A47: TC-PROMO-09 | B47: Coupon / Promotion | C47: Promotion | D47: amount vs percent | E47: API | F47: Positive | G47: Medium | H47: Blocked | I47: Yes | K47: amount/percent — รอ valid code ที่ apply ได้จริง | L47: login | M47: TD-11, TD-12 | N47: 1.Apply แต่ละแบบ ดูยอดหัก | O47: amount=บาทคงที่; percent=%×ยอด | P47: `discountAmount:1707-1770` | Q47: parameterize
A48: TC-PROMO-10 | B48: Coupon / Promotion | C48: Promotion | D48: re-validate ตอนสั่ง | E48: Integration | F48: API Error | G48: High | H48: Blocked | I48: Yes | K48: re-validate ตอนกดสั่ง — รอ data + สร้าง order จริง | L48: login, สลับยอด/คูปองให้ขัด | M48: TD-07/13 | N48: 1.Apply ผ่าน 2.กดชำระ | O48: order reject "Error validating coupon code(WME01): ..." | P48: `OrderController:store:~320` | Q48: —
A49: TC-AUTH-01-R | B49: Register / Auth (during checkout) | C49: Auth | D49: สมัครตอน checkout | E49: Integration | F49: Positive | G49: Medium | H49: Not Started | L49: checkout, email ใหม่ | M49: add_to_new_user=1, password ≥8 | N49: 1.ติ๊กสมัคร 2.ตั้ง password 3.สั่ง | O49: `register_new_web_user` สร้าง user; login ภายหลังได้ | P49: `OrderController:register_new_web_user` | Q49: —
A50: TC-AUTH-03 | B50: Register / Auth (during checkout) | C50: Auth | D50: email ซ้ำตอนสมัคร | E50: API | F50: Negative | G50: High | H50: Not Started | L50: มี email ที่ลงทะเบียนแล้ว | M50: add_to_new_user=1, email=ซ้ำ | N50: 1.ติ๊กสมัคร + email ซ้ำ 2.สั่ง | O50: reject "อีเมล์แอดเดรส ... ถูกใช้ไปแล้ว" | P50: `Rules/WebUserExists::validate` | Q50: —
A51: TC-AUTH-04 | B51: Register / Auth (during checkout) | C51: Auth | D51: token ไม่ถูกต้อง | E51: API | F51: Permission | G51: High | H51: Not Started | L51: — | M51: web_user_token ปลอม + coupon_code | N51: 1.POST order ด้วย token ผิด | O51: reject "Web User Token ไม่ถูกต้อง" | P51: `WebUserExists::validToken` | Q51: —
A52: TC-AUTH-05 | B52: Register / Auth (during checkout) | C52: Auth | D52: สมัคร password สั้น/ไม่ตรง | E52: API/UI | F52: Validation | G52: Medium | H52: Not Started | L52: checkout | M52: password="123" | N52: 1.ติ๊กสมัคร + password สั้น 2.สั่ง | O52: reject "รหัสผ่านต้องยาวอย่างน้อย 8" | P52: `OrderController:store`, `CheckoutForm:502` | Q52: —
A53: TC-PAY-01-R | B53: Payment | C53: Payment | D53: QR/โอน + แจ้งชำระ | E53: Integration | F53: Positive | G53: High | H53: Not Started | L53: order รอชำระ (TD-20) | M53: bank_id 1-4 + สลิป (TD-23) | N53: 1.เปิด `/payment/{tracking_id}` 2.เลือกธนาคาร 3.แนบสลิป | O53: แสดง QR/บัญชี; แจ้งชำระ → `/order/accept-payment-infos`; **ไม่ตัดเงินอัตโนมัติ** | P53: `payment/[tracking_id]`, `accept_payment_infos` | Q53: หยุดก่อนยืนยัน
A54: TC-PAY-02-R | B54: Payment | C54: Payment | D54: บัตร fee (env) | E54: Integration | F54: Boundary | G54: High | H54: Not Started | L54: ผ่าน checkout, ยอดทราบค่า (TD-18) | M54: method=2, ยอด=X | N54: 1.เลือกบัตร 2.ดูยอด | O54: fee = X×`CREDIT_CARD_SERVICE_FEE_PERCENTAGE`/100 (**ยืนยันค่า env**) | P54: `get_total_payment:~1625` | Q54: **แก้ assumption 3% ตายตัว**
A55: TC-PAY-03 | B55: Payment | C55: Payment | D55: ไม่ทำ transaction จริง | E55: Manual Exploratory | F55: Positive (safety gate) | G55: High | H55: Not Started | L55: อยู่หน้าชำระเงิน | M55: — | N55: 1.หยุดก่อนยืนยันชำระจริง | O55: ไม่มี transaction จริงใน env ทดสอบ | P55: กฎความปลอดภัย | Q55: gate กลางทุก payment TC
A56: TC-PAY-04 | B56: Payment | C56: Payment | D56: fee = total×env% | E56: Integration | F56: Boundary | G56: High | H56: Not Started | L56: ผ่าน checkout (TD-18) | M56: method=2, ยอด=X | N56: 1.เลือกบัตร 2.ดูยอด | O56: fee=X×env%/100; total+fee แสดงก่อนชำระ | P56: `get_total_payment:~1625` | Q56: ยืนยัน env
A57: TC-PAY-05 | B57: Payment | C57: Payment | D57: สลิปบังคับ | E57: API | F57: Validation | G57: High | H57: Not Started | L57: order รอชำระ (TD-20) | M57: bank_id=1, ไม่มี media_id | N57: 1.POST `/order/accept-payment-infos` ไม่แนบสลิป | O57: reject (media_id required_with bank_id) | P57: `accept_payment_infos:rules` | Q57: —
A58: TC-PAY-06 | B58: Payment | C58: Payment | D58: bank_id → payment.type | E58: API | F58: Positive | G58: Medium | H58: Not Started | L58: order รอชำระ | M58: bank_id 0/1/2/3/4 | N58: 1.แจ้งชำระแต่ละธนาคาร | O58: payment.type map ถูก (4/2/3/1/6) | P58: `accept_payment_infos:switch` | Q58: parameterize
A59: TC-PAY-07 | B59: Payment | C59: Payment | D59: status_payment โอน=1/บัตร=2 | E59: API | F59: Positive | G59: Medium | H59: Not Started | L59: order รอชำระ | M59: โอน vs 2c2p | N59: 1.แจ้งชำระ | O59: status_payment = 1(โอน)/2(บัตร) | P59: `accept_payment_infos:~1010` | Q59: —
A60: TC-PAY-09 | B60: Payment | C60: Payment | D60: transfer date/time ผิด | E60: API | F60: Validation | G60: Medium | H60: Not Started | L60: order รอชำระ | M60: date="2026/01/01" | N60: 1.แจ้งชำระ format ผิด | O60: reject "...รูปแบบ Y-m-d / H:i" | P60: `accept_payment_infos:rules` | Q60: —
A61: TC-PAY-10 | B61: Payment | C61: Payment | D61: 2C2P fail | E61: API | F61: API Error | G61: Medium | H61: Script Done | I61: Yes | K61: tests/regression/TC-PAY-CARD-NEG_card-declined.robot — PASS (RF, 2c2p sandbox declined; gated on PROD) | L61: order รอชำระ | M61: success=false, tracking_id | N61: 1.callback fail | O61: ส่งเมล fail, return ok | P61: `payment_fails:1147` | Q61: sandbox
A62: TC-ORD-01a-R | B62: Order Success / Tracking | C62: Order Success | D62: หน้า success | E62: UI | F62: Positive | G62: Medium | H62: Not Started | L62: order สำเร็จ (sandbox) | M62: tracking_id | N62: 1.เปิด `/payment/success/{tracking_id}` | O62: แสดงเลขออเดอร์/สรุป | P62: `app/payment/success/[tracking_id]` | Q62: —
A63: TC-ORD-01b-R | B63: Order Success / Tracking | C63: Order Success | D63: email ยืนยัน | E63: Integration | F63: Positive | G63: Medium | H63: Not Started | L63: order สำเร็จ | M63: email ผู้สั่ง | N63: 1.สั่งสำเร็จ 2.ตรวจเมล | O63: `SendOrderCreatedEmailJob` dispatch + ได้เมล | P63: `OrderController:store:~440` | Q63: ตรวจที่ mail server
A64: TC-TRK-01a-R | B64: Order Success / Tracking | C64: Tracking | D64: ค้นด้วย tracking_id | E64: Integration | F64: Positive | G64: Medium | H64: Not Started | L64: TD-22 (service พร้อม) | M64: tracking_id | N64: 1.เปิด `/tracking?tracking_id=` 2.ค้นหา | O64: แสดงสถานะตาม status_payment | P64: `app/tracking/page.tsx`; service=`Not verifiable from code` | Q64: ขอ spec service
A65: TC-TRK-02 | B65: Order Success / Tracking | C65: Tracking | D65: order_code + เบอร์/อีเมล | E65: Integration | F65: Positive | G65: Medium | H65: Script Done | I65: Yes | K65: tests/tracking/TC-TRK-01_track-by-order-code.robot — order_code + phone (RF). PROD-only: skip บน staging (ต้องมี known order); robot tag TC-TRK-01 | L65: TD-22 | M65: order_code + phone_or_email | N65: 1.กรอกคู่ข้อมูล 2.ค้นหา | O65: แสดงสถานะ | P65: `tracking/page.tsx:36-44` | Q65: path ที่ 2
A66: TC-TRK-03 | B66: Order Success / Tracking | C66: Tracking | D66: ข้อมูลผิด | E66: Integration | F66: Negative | G66: Medium | H66: Script Done | I66: Yes | K66: tests/tracking/TC-TRK-04_invalid-lookup.robot — PASS (RF, notFound + no leak; robot tag TC-TRK-04) | L66: — | M66: tracking_id ปลอม | N66: 1.ค้นหา | O66: branch notFound, ไม่ leak ข้อมูลผู้อื่น | P66: `tracking/page.tsx:55-58` | Q66: —
A67: TC-TRK-04 | B67: Order Success / Tracking | C67: Tracking | D67: branch status_payment | E67: Integration | F67: Positive | G67: Medium | H67: Not Started | L67: order หลายสถานะ (TD-20/21) | M67: status 0/1 vs 2/3/4 | N67: 1.เปิด tracking | O67: 0/1→`result-notpayment`; 2-4→`result` | P67: `tracking/page.tsx:140-160` | Q67: —
A68: TC-SEC-01 | B68: Cross-cutting: API Error / Session / Security / Responsive | C68: Security | D68: consent bypass (BE) | E68: API | F68: Security | G68: High | H68: Not Started | L68: — | M68: payload ไม่มี privacy_policy_accepted | N68: 1.POST `/api/order` ตรง | O68: **BE ไม่ block → ผ่าน** = ความเสี่ยง bypass; แจ้ง dev เพิ่ม rule | P68: `OrderController:store` (ไม่มี privacy rule) | Q68: =TC-CHK-05 ฝั่ง API
A69: TC-SEC-02 | B69: Cross-cutting: API Error / Session / Security / Responsive | C69: Security | D69: phone bypass FE | E69: API | F69: FE/BE Inconsistency | G69: Medium | H69: Not Started | L69: — | M69: `+66812345678` | N69: 1.POST `/api/order` ตรง | O69: FE reject แต่ BE รับ | P69: FE vs BE regex | Q69: —
A70: TC-SEC-03 | B70: Cross-cutting: API Error / Session / Security / Responsive | C70: Security | D70: XSS/SQLi ในป้าย/ศาลา | E70: API | F70: Security | G70: Medium | H70: Not Started | L70: — | M70: `<script>alert(1)</script>`, `' OR '1'='1` | N70: 1.กรอก submit | O70: Eloquent parameterized; ไม่ execute/ไม่ 500 (`Not verifiable from code` — ต้อง execute) | P70: `OrderController:store` (ไม่พบ explicit sanitize) | Q70: basic security smoke
A71: TC-API-01 | B71: Cross-cutting: API Error / Session / Security / Responsive | C71: API Error | D71: ERP 422 | E71: Integration | F71: API Error | G71: High | H71: Not Started | L71: mock ERP 422 (TD-24) | M71: — | N71: 1.submit order | O71: proxy คืน `{error:true,...}` → `openErrorModal` แสดง | P71: `pages/api/order.ts:catch`, `onCreateOrder:else` | Q71: mock
A72: TC-API-02 | B72: Cross-cutting: API Error / Session / Security / Responsive | C72: API Error | D72: ERP 500/timeout | E72: Integration | F72: API Error | G72: High | H72: Not Started | L72: mock ERP 500/timeout (TD-24) | M72: — | N72: 1.submit order/total-payment | O72: modal error, ไม่ crash | P72: `pages/api/total-payment.ts:catch`, interceptors | Q72: mock
A73: TC-SESS-01 | B73: Cross-cutting: API Error / Session / Security / Responsive | C73: Session | D73: 401 handling | E73: Integration | F73: Session | G73: High | H73: Not Started | L73: login | M73: mock 401 จาก ERP_API (TD-24) | N73: 1.เรียก API ระหว่าง flow | O73: `clearStorage()` + reload | P73: `instance.ts` ERP_API interceptor | Q73: —
A74: TC-SESS-02 | B74: Cross-cutting: API Error / Session / Security / Responsive | C74: Session | D74: cleanup messageCard keys | E74: UI | F74: Session | G74: Medium | H74: Not Started | L74: มีของ + กรอกป้าย | M74: — | N74: 1.ลบสินค้า/สั่งสำเร็จ | O74: localStorage `messageCardModal-*` ถูกลบ | P74: `useCart:43-53`, `onCreateOrder:cleanup` | Q74: กันข้อมูลป้ายเก่ารั่ว
A75: TC-ERR-01 | B75: Cross-cutting: API Error / Session / Security / Responsive | C75: Error | D75: 404 page | E75: UI | F75: Negative | G75: Medium | H75: Script Done | I75: Yes | K75: tests/checkout/TC-ERR-01_unknown-url-404.robot — PASS (RF) | L75: — | M75: `/this-page-does-not-exist/` | N75: 1.เปิด URL ไม่มีจริง | O75: หน้า 404 ที่ออกแบบ + ลิงก์กลับ | P75: `app/not-found.tsx` | Q75: keep
A76: TC-ERR-02 | B76: Cross-cutting: API Error / Session / Security / Responsive | C76: Responsive | D76: mobile flow | E76: Manual Exploratory | F76: Regression | G76: Medium | H76: Not Started | L76: — | M76: viewport 375×812 | N76: 1.ทำ flow สั่งซื้อบนมือถือ | O76: layout ไม่แตก, ปุ่ม/ฟอร์มใช้ได้, hamburger ใช้ได้ | P76: `CartSummaryMobile`, `MobileOrderSummary` | Q76: manual

Sheet A-Account-Auth
A1: Test Case ID | B1: Group | C1: Module | D1: Feature | E1: Test Level | F1: Test Type | G1: Priority | H1: Script Status | I1: Automatable | J1: Assignee | K1: Script File / Notes | L1: Preconditions | M1: Test Data | N1: Test Steps | O1: Expected Result | P1: Code Evidence | Q1: Remark
A2: TC-LOGIN-01 | B2: Account / Auth | C2: Login | D2: login สำเร็จ | E2: UI | F2: Positive | G2: High | H2: Script Done | I2: Yes | K2: tests/auth/login/TC-LOGIN-01_login-success.robot | L2: TD-30 | M2: TD-30 | N2: 1.เปิด AuthModal 2.กรอก email+password ถูก 3.กดเข้าสู่ระบบ | O2: modal ปิด, modal สำเร็จ "เข้าสู่ระบบสำเร็จ", redirect /user-infos, header แสดงชื่อผู้ใช้ | P2: LoginForm.tsx:62-81
A3: TC-LOGIN-02 | B3: Account / Auth | C3: Login | D3: ฟิลด์ว่าง | E3: UI | F3: Validation | G3: Medium | H3: Script Done | I3: Yes | K3: tests/auth/login/TC-LOGIN-02_empty-fields.robot | L3: - | N3: 1.เว้น email/password 2.กดเข้าสู่ระบบ | O3: error "กรุณาระบุอีเมลและรหัสผ่าน", ไม่ยิง API | P3: LoginSchema
A4: TC-LOGIN-03 | B4: Account / Auth | C4: Login | D4: รหัส/อีเมลผิด | E4: UI | F4: Negative | G4: High | H4: Script Done | I4: Yes | K4: tests/auth/login/TC-LOGIN-03_invalid-credentials.robot | L4: TD-30 | M4: TD-30 | N4: กรอก password ผิด → submit | O4: error "รหัสหรืออีเมลผู้ใช้ไม่ถูกต้อง", status=failed | P4: auth.ts:127-146
A5: TC-LOGIN-04 | B5: Account / Auth | C5: Login | D5: อีเมลยังไม่ยืนยัน | E5: UI | F5: Negative | G5: High | H5: Blocked | I5: Yes | K5: tests/auth/login/TC-LOGIN-04_unverified-email.robot | L5: TD-31 | M5: TD-31 | N5: login ด้วย user ที่ยังไม่ยืนยัน | O5: error "อีเมลผู้ใช้ ยังไม่ได้ยืนยันตัวตน / กรุณาตรวจสอบอีเมล" | P5: LoginForm.tsx
A6: TC-LOGIN-05 | B6: Account / Auth | C6: Login | D6: Remember Me = ON | E6: UI | F6: Functional | G6: Medium | H6: Script Done | I6: Yes | K6: tests/auth/login/TC-LOGIN-05_remember-me-on.robot | L6: TD-30 | M6: TD-30 | N6: ติ๊ก rememberMe → login → ปิด browser → เปิดใหม่ | O6: token อยู่ใน localStorage, ยัง login ค้าง | P6: auth.ts:132
A7: TC-LOGIN-06 | B7: Account / Auth | C7: Login | D7: Remember Me = OFF | E7: UI | F7: Functional | G7: Medium | H7: Script Done | I7: Yes | K7: tests/auth/login/TC-LOGIN-06_remember-me-off.robot | L7: TD-30 | M7: TD-30 | N7: ไม่ติ๊ก → login → refresh tab | O7: token อยู่ใน sessionStorage เท่านั้น | P7: auth.ts:132
A8: TC-LOGIN-07 | B8: Account / Auth | C8: Login | D8: guest cart sync หลัง login | E8: Integration | F8: Positive | G8: Medium | H8: Script Done | I8: Yes | K8: tests/auth/login/TC-LOGIN-07_guest-cart-sync.robot | L8: TD-30 + มีของในตะกร้า (guest) | M8: TD-30 | N8: เพิ่มสินค้าแบบ guest → login | O8: cart merge จาก user.cart ไม่หาย (synUserCart) | P8: LoginForm.tsx:64-66
A9: TC-LOGIN-08 | B9: Account / Auth | C9: Login | D9: กันกดซ้ำ | E9: UI | F9: Race | G9: Low | H9: Script Done | I9: Yes | K9: tests/auth/login/TC-LOGIN-08_double-submit-guard.robot | L9: TD-30 | M9: TD-30 | N9: กดปุ่มเข้าสู่ระบบรัว | O9: ปุ่ม disable ("กำลังเข้าสู่ระบบ"), ยิง API ครั้งเดียว | P9: LoginForm.tsx
A10: TC-REG-01 | B10: Account / Auth | C10: Register | D10: สมัครสำเร็จ | E10: UI | F10: Positive | G10: High | H10: Script Done | I10: Yes | K10: tests/auth/register/TC-REG-01_register-success.robot | L10: TD-32 | M10: TD-32 | N10: กรอก email ใหม่ + password ผ่านกฎ + ติ๊ก privacy → สมัคร | O10: modal สำเร็จ "ลงทะเบียนสำเร็จ / กรุณาตรวจสอบอีเมลเพื่อยืนยัน", ไม่ auto-login | P10: RegisterForm.tsx:46-55
A11: TC-REG-02 | B11: Account / Auth | C11: Register | D11: email ซ้ำ | E11: UI | F11: Negative | G11: High | H11: Script Done | I11: Yes | K11: tests/auth/register/TC-REG-02_duplicate-email.robot | L11: TD-30 | M11: TD-30 | N11: สมัครด้วย email ที่มีแล้ว | O11: error จาก backend ใต้ช่อง email | P11: auth.ts:41-56
A12: TC-REG-03 | B12: Account / Auth | C12: Register | D12: password สั้น (<8) | E12: UI | F12: Boundary | G12: High | H12: Script Done | I12: Yes | K12: tests/auth/register/TC-REG-03_password-too-short.robot | L12: - | N12: password 7 ตัว | O12: "รหัสผ่านต้องมีความยาวเกิน 8 ตัวอักษร" | P12: validation/checkout.ts:74-83
A13: TC-REG-04 | B13: Account / Auth | C13: Register | D13: password ยาว (>16) | E13: UI | F13: Boundary | G13: Medium | H13: Script Done | I13: Yes | K13: tests/auth/register/TC-REG-04_password-too-long.robot | L13: - | N13: password 17 ตัว | O13: "รหัสผ่านมีความยาวเกิน 16 ตัวอักษร" | P13: validation/checkout.ts:74-83
A14: TC-REG-05 | B14: Account / Auth | C14: Register | D14: ขาดพิมพ์ใหญ่ | E14: UI | F14: Validation | G14: Medium | H14: Script Done | I14: Yes | K14: tests/auth/register/TC-REG-05_password-no-uppercase.robot | L14: - | N14: password ไม่มี A-Z | O14: "รหัสผ่านต้องมีตัวอักษรพิมพ์ใหญ่อย่างน้อย 1 ตัว" | P14: validation/checkout.ts:74-83
A15: TC-REG-06 | B15: Account / Auth | C15: Register | D15: ขาดพิมพ์เล็ก | E15: UI | F15: Validation | G15: Medium | H15: Script Done | I15: Yes | K15: tests/auth/register/TC-REG-06_password-no-lowercase.robot | L15: - | N15: ไม่มี a-z | O15: "...พิมพ์เล็กอย่างน้อย 1 ตัว" | P15: validation/checkout.ts:74-83
A16: TC-REG-07 | B16: Account / Auth | C16: Register | D16: ขาดตัวเลข | E16: UI | F16: Validation | G16: Medium | H16: Script Done | I16: Yes | K16: tests/auth/register/TC-REG-07_password-no-digit.robot | L16: - | N16: ไม่มี 0-9 | O16: "...ตัวเลขอย่างน้อย 1 ตัว" | P16: validation/checkout.ts:74-83
A17: TC-REG-08 | B17: Account / Auth | C17: Register | D17: ขาดอักขระพิเศษ | E17: UI | F17: Validation | G17: Medium | H17: Script Done | I17: Yes | K17: tests/auth/register/TC-REG-08_password-no-special.robot | L17: - | N17: ไม่มี special char | O17: "...อักขระพิเศษอย่างน้อย 1 ตัว" | P17: validation/checkout.ts:74-83
A18: TC-REG-09 | B18: Account / Auth | C18: Register | D18: มีช่องว่าง | E18: UI | F18: Validation | G18: Medium | H18: Script Done | I18: Yes | K18: tests/auth/register/TC-REG-09_password-has-space.robot | L18: - | N18: password มี space | O18: "รหัสผ่านต้องไม่มีช่องว่าง" | P18: validation/checkout.ts:74-83
A19: TC-REG-10 | B19: Account / Auth | C19: Register | D19: email format ผิด | E19: UI | F19: Validation | G19: Medium | H19: Script Done | I19: Yes | K19: tests/auth/register/TC-REG-10_invalid-email-format.robot | L19: - | N19: "abc", "a@", มี space | O19: "กรุณากรอกอีเมลที่ถูกต้อง" / "ไม่สามารถใส่ค่าว่างใน Email ได้" | P19: validation/checkout.ts
A20: TC-REG-11 | B20: Account / Auth | C20: Register | D20: ไม่ติ๊ก privacy | E20: UI | F20: Validation | G20: High | H20: Script Done | I20: Yes | K20: tests/auth/register/TC-REG-11_privacy-not-accepted.robot | L20: - | N20: กรอกครบ ไม่ติ๊ก → สมัคร | O20: "กรุณายอมรับนโยบายความเป็นส่วนตัว" | P20: RegisterSchema
A21: TC-REG-12 | B21: Account / Auth | C21: Register | D21: toggle show password | E21: UI | F21: Functional | G21: Low | H21: Script Done | I21: Yes | K21: tests/auth/register/TC-REG-12_toggle-password-visibility.robot | L21: - | N21: คลิก eye icon | O21: สลับ password ↔ text | P21: RegisterForm.tsx
A22: TC-REG-13 | B22: Account / Auth | C22: Register | D22: privacy link เปิดแท็บใหม่ | E22: UI | F22: Functional | G22: Low | H22: Script Done | I22: Yes | K22: tests/auth/register/TC-REG-13_privacy-link-new-tab.robot | L22: - | N22: คลิกลิงก์นโยบาย | O22: เปิด /นโยบายความเป็นส่วนตัว/ target=_blank | P22: RegisterForm.tsx
A23: TC-CFM-01 | B23: Account / Auth | C23: Email Confirm | D23: token ถูก | E23: UI | F23: Positive | G23: High | H23: Not Started | I23: Yes | L23: TD-33 valid | M23: TD-33 | N23: เปิดลิงก์จากเมล | O23: "ยืนยันอีเมลสำเร็จ" + countdown 5→0 → redirect / | P23: user-confirm-email/Content.tsx:16-35
A24: TC-CFM-02 | B24: Account / Auth | C24: Email Confirm | D24: ไม่มี token | E24: UI | F24: Negative | G24: Medium | H24: Not Started | I24: Yes | L24: - | N24: เปิด /user-confirm-email ไม่มี k | O24: DEF-A1: หน้าเงียบ ไม่มีข้อความ (ควรมี error) — flag UX | P24: user-confirm-email/Content.tsx | Q24: DEF-A1
A25: TC-CFM-03 | B25: Account / Auth | C25: Email Confirm | D25: token ผิด/หมดอายุ | E25: UI | F25: Negative | G25: Medium | H25: Not Started | I25: Yes | L25: TD-33 expired | M25: TD-33 | N25: เปิดลิงก์ token ปลอม | O25: API fail → ปัจจุบันเงียบ — flag | P25: user-confirm-email/Content.tsx | Q25: DEF-A1
A26: TC-CFM-04 | B26: Account / Auth | C26: Email Confirm | D26: ยืนยันซ้ำ | E26: API | F26: Negative | G26: Low | H26: Not Started | I26: Yes | L26: TD-33 used | M26: TD-33 | N26: เรียก confirm ซ้ำ | O26: idempotent หรือ error ไม่ crash | P26: confirm-email endpoint
A27: TC-CFM-05 | B27: Account / Auth | C27: Email Confirm | D27: navigate ออกระหว่าง countdown | E27: UI | F27: Functional | G27: Low | H27: Not Started | I27: Partial | L27: TD-33 valid | M27: TD-33 | N27: ยืนยันสำเร็จ → คลิกออกก่อนครบ 5 วิ | O27: timer clear ไม่ redirect ทับ | P27: useEffect cleanup
A28: TC-FGT-01 | B28: Account / Auth | C28: Forgot Password | D28: ส่งลิงก์สำเร็จ | E28: UI | F28: Positive | G28: High | H28: Script Done | I28: Yes | K28: tests/auth/forget/TC-FGT-01_send-reset-link-success.robot — PASS (ส่งอีเมลจริงไป TD-30) | L28: TD-30 | M28: TD-30 | N28: กรอก email → ส่ง | O28: "ส่งลิงก์สำเร็จ กรุณาตรวจสอบอีเมล", ฟอร์มซ่อน | P28: forget-password/page.tsx:14-31
A29: TC-FGT-02 | B29: Account / Auth | C29: Forgot Password | D29: error path | E29: UI | F29: Negative | G29: Medium | H29: Blocked | I29: Partial | K29: error message ครอบโดย TC-FGT-03 แล้ว; การ mock 500 จริงรอ API track (RequestsLibrary/CDP) | L29: mock 500 | M29: TD-24 | N29: ทำให้ API error | O29: "เกิดข้อผิดพลาดในการส่งลิงก์ กรุณาลองใหม่อีกครั้ง" | P29: forget-password/page.tsx
A30: TC-FGT-03 | B30: Account / Auth | C30: Forgot Password | D30: ช่องว่าง/ไม่ใช่อีเมล | E30: UI/API | F30: Negative | G30: Medium | H30: Script Done | I30: Yes | K30: tests/auth/forget/TC-FGT-03_invalid-email-error.robot — PASS (ครอบ error ของ FGT-02 ด้วย) | L30: - | N30: กรอกว่าง/"abc" → ส่ง | O30: ไม่มี client validation → BE ต้องจัดการ (ตรวจ response) | P30: forget-password/page.tsx
A31: TC-FGT-04 | B31: Account / Auth | C31: Forgot Password | D31: กันกดซ้ำ | E31: UI | F31: Race | G31: Low | H31: Blocked | I31: Partial | K31: FINDING: ปุ่มเปลี่ยน text เป็น "กำลังดำเนินการ" แต่ disabled=false (ไม่ได้กันกดซ้ำจริง) — ยืนยันกับ dev | L31: TD-30 | M31: TD-30 | N31: กดส่งรัว | O31: ปุ่ม disable ("กำลังดำเนินการ") | P31: forget-password/page.tsx
A32: TC-RST-01 | B32: Account / Auth | C32: Reset Password | D32: รีเซ็ตสำเร็จ | E32: UI | F32: Positive | G32: High | H32: Not Started | I32: Yes | L32: TD-34 valid | M32: TD-34 | N32: เปิดลิงก์ → กรอกรหัสใหม่ → ยืนยัน | O32: "เปลี่ยนรหัสผ่านสำเร็จแล้ว" | P32: user-reset-password/Content.tsx:19-44
A33: TC-RST-02 | B33: Account / Auth | C33: Reset Password | D33: ไม่มี token | E33: UI | F33: Negative | G33: Medium | H33: Not Started | I33: Yes | L33: - | N33: เปิดหน้าไม่มี k → submit | O33: alert("Token is missing in the URL") | P33: user-reset-password/Content.tsx
A34: TC-RST-03 | B34: Account / Auth | C34: Reset Password | D34: token ผิด/หมดอายุ/ใช้แล้ว | E34: UI | F34: Negative | G34: Medium | H34: Not Started | I34: Yes | L34: TD-34 expired/used | M34: TD-34 | N34: ใช้ token ปลอม | O34: "เกิดข้อผิดพลาดในการเปลี่ยนรหัสผ่าน" | P34: user-reset-password/Content.tsx
A35: TC-RST-04 | B35: Account / Auth | C35: Reset Password | D35: placeholder ผิด | E35: UI | F35: Bug | G35: Low | H35: Not Started | I35: Yes | L35: - | N35: สังเกต placeholder | O35: DEF-A2: เขียน "กรอกรหัสผ่านเดิม" แต่จริงต้องกรอกรหัสใหม่ — flag | P35: Content.tsx:57 | Q35: DEF-A2
A36: TC-RST-05 | B36: Account / Auth | C36: Reset Password | D36: complexity FE vs BE | E36: API | F36: Validation | G36: Medium | H36: Not Started | I36: Yes | L36: TD-34 valid | M36: TD-34 | N36: ส่ง password สั้น/ไม่ครบกฎ | O36: FE ไม่บังคับ → ตรวจว่า BE บังคับ min 8 + กฎหรือไม่ | P36: เทียบกับ RegisterSchema | Q36: DEF-A3
A37: TC-USER-01 | B37: Account / Auth | C37: User Info | D37: เข้าโดยไม่ login | E37: UI | F37: Security | G37: High | H37: Script Done | I37: Yes | K37: tests/auth/user/TC-USER-01_guest-no-access.robot — PASS | L37: guest | M37: TD-01 | N37: เปิด /user-infos ตรง | O37: หน้าว่าง/redirect (ปัจจุบัน {isAuth && ...} → ว่าง) — ตรวจ behavior | P37: user-infos/page.tsx
A38: TC-USER-02 | B38: Account / Auth | C38: User Info | D38: prefill ข้อมูล | E38: UI | F38: Positive | G38: Medium | H38: Script Done | I38: Yes | K38: tests/auth/user/TC-USER-02_prefill.robot — PASS | L38: TD-30 | M38: TD-30 | N38: เปิดหน้าหลัง login | O38: ฟอร์ม prefill จาก user (name/phone/address/receipt) | P38: UserInforSection.tsx
A39: TC-USER-03 | B39: Account / Auth | C39: User Info | D39: update ข้อมูลส่วนตัว | E39: UI | F39: Positive | G39: High | H39: Not Started | I39: Yes | L39: TD-30 | M39: TD-30 | N39: แก้ name/phone/address → อัปเดต | O39: toast "อัปเดตข้อมูลส่วนตัวสำเร็จ", refetch | P39: UserInforSection.tsx
A40: TC-USER-04 | B40: Account / Auth | C40: User Info | D40: name ว่าง | E40: UI | F40: Validation | G40: Medium | H40: Not Started | I40: Yes | L40: TD-30 | M40: TD-30 | N40: ลบ name → อัปเดต | O40: "กรุณากรอกชื่อ-สกุล" | P40: validatePersonalInfo
A41: TC-USER-05 | B41: Account / Auth | C41: User Info | D41: email disabled | E41: UI | F41: Functional | G41: Low | H41: Script Done | I41: Yes | K41: tests/auth/user/TC-USER-05_email-readonly.robot — PASS | L41: TD-30 | M41: TD-30 | N41: ลองแก้ช่อง email | O41: แก้ไม่ได้ (gray, read-only) | P41: UserInforSection.tsx
A42: TC-USER-06 | B42: Account / Auth | C42: User Info | D42: ใบกำกับ required | E42: UI | F42: Validation | G42: Medium | H42: Not Started | I42: Yes | L42: TD-30 | M42: TD-30 | N42: เว้น issue_to/tax_id/email/address → อัปเดต | O42: error ใต้แต่ละช่องที่ขาด | P42: validateReceiptInfo
A43: TC-USER-07 | B43: Account / Auth | C43: User Info | D43: tax_id boundary 13 | E43: UI | F43: Boundary | G43: Medium | H43: Not Started | I43: Yes | L43: TD-30 | M43: TD-30 | N43: พิมพ์ tax_id 14 หลัก | O43: บล็อกพิมพ์เกิน 13 + error ถ้าเกิน | P43: handleNestedChange:231
A44: TC-USER-08 | B44: Account / Auth | C44: User Info | D44: เปลี่ยนรหัส สำเร็จ | E44: UI | F44: Positive | G44: High | H44: Not Started | I44: Yes | L44: TD-30 | M44: TD-30 | N44: เปิด modal → currentPwd ถูก + newPwd ผ่านกฎ | O44: toast "เปลี่ยนรหัสผ่านสำเร็จ", modal ปิด | P44: PasswordChangeModal.tsx
A45: TC-USER-09 | B45: Account / Auth | C45: User Info | D45: รหัสเดิมผิด | E45: UI | F45: Negative | G45: High | H45: Not Started | I45: Yes | L45: TD-30 | M45: TD-30 | N45: currentPwd ผิด | O45: "รหัสเดิมไม่ถูกต้อง" | P45: PasswordChangeModal.tsx
A46: TC-USER-10 | B46: Account / Auth | C46: User Info | D46: newPwd ไม่ผ่านกฎ | E46: UI | F46: Validation | G46: Medium | H46: Not Started | I46: Yes | L46: TD-30 | M46: TD-30 | N46: newPwd อ่อน | O46: error เหมือน register (ครบ 7 กรณี) | P46: ChangePasswordSchema
A47: TC-USER-11 | B47: Account / Auth | C47: User Info | D47: EDM checkbox | E47: UI | F47: Functional | G47: Low | H47: Not Started | I47: Yes | L47: TD-30 | M47: TD-30 | N47: ติ๊ก/ไม่ติ๊ก → อัปเดต | O47: accept_for_edm persist | P47: UserInforSection.tsx
A48: TC-USER-12 | B48: Account / Auth | C48: User Info | D48: logout | E48: UI | F48: Functional | G48: High | H48: Script Done | I48: Yes | K48: tests/auth/user/TC-USER-12_logout.robot — PASS | L48: TD-30 | M48: TD-30 | N48: กด Log Out | O48: clear state+storage, redirect / | P48: handleLogOut
A49: TC-USER-13 | B49: Account / Auth | C49: User Info | D49: tab switch desktop/mobile | E49: UI | F49: Functional | G49: Low | H49: Script Done | I49: Yes | K49: tests/auth/user/TC-USER-13_tab-switch.robot — PASS | L49: TD-30 | M49: TD-30 | N49: สลับแท็บข้อมูล/ออเดอร์ | O49: render ถูก, mobile accordion | P49: UserInforSection.tsx
A50: TC-OH-01 | B50: Account / Auth | C50: Order History | D50: แสดง pending+completed | E50: UI | F50: Positive | G50: Medium | H50: Blocked | I50: Yes | K50: รอ user ที่มีออเดอร์ (TD-39) จาก dev | L50: TD-39 | M50: TD-39 | N50: เปิดแท็บรายการสั่งซื้อ | O50: 2 section แสดง order code/รายการ/จำนวน + badge pending count | P50: OrdersSection.tsx
A51: TC-OH-02 | B51: Account / Auth | C51: Order History | D51: empty state | E51: UI | F51: Positive | G51: Low | H51: Script Done | I51: Yes | K51: tests/auth/user/TC-OH-02_order-history-empty.robot — PASS (inoobeam ไม่มีออเดอร์) | L51: user ไม่มีออเดอร์ | M51: TD-30 | N51: เปิดแท็บ | O51: "- ยังไม่มีรายการสั่งซื้อ -" ทั้ง 2 section | P51: OrdersSection.tsx
A52: TC-OH-03 | B52: Account / Auth | C52: Order History | D52: copy order code | E52: UI | F52: Functional | G52: Low | H52: Blocked | I52: Yes | K52: copy order code — รอ user ที่มีออเดอร์ (TD-39) | L52: TD-39 | M52: TD-39 | N52: คลิกปุ่ม copy | O52: clipboard ได้ค่า + "คัดลอกเลขออเดอร์สำเร็จ" 1.5 วิ | P52: OrdersSection.tsx
A53: TC-OH-04 | B53: Account / Auth | C53: Order History | D53: ลิงก์ติดต่อ LINE | E53: UI | F53: Functional | G53: Low | H53: Blocked | I53: Yes | K53: LINE link — รอ user ที่มีออเดอร์ (TD-39) | L53: TD-39 | M53: TD-39 | N53: คลิก "ติดต่อทีมงานผ่าน LINE" | O53: เปิด /line แท็บใหม่ | P53: OrdersSection.tsx

Sheet B-MessageCard
A1: Test Case ID | B1: Group | C1: Module | D1: Feature | E1: Test Level | F1: Test Type | G1: Priority | H1: Script Status | I1: Automatable | J1: Assignee | K1: Script File / Notes | L1: Preconditions | M1: Test Data | N1: Test Steps | O1: Expected Result | P1: Code Evidence | Q1: Remark
A2: TC-CARD-01 | B2: Message Card / Ribbon | C2: Message Card | D2: preview real-time | E2: UI | F2: Positive | G2: High | H2: Not Started | I2: Yes | L2: สินค้าใน checkout | M2: TD-03 | N2: เปิด modal → พิมพ์บรรทัด 1 | O2: หลัง 888ms preview รูปอัปเดต (base64) | P2: MessageCardModal.tsx
A3: TC-CARD-02 | B3: Message Card / Ribbon | C3: Message Card | D3: เปลี่ยน tone/format/align | E3: UI | F3: Functional | G3: Medium | H3: Not Started | I3: Yes | L3: เปิด modal | M3: TD-03 | N3: สลับขาว/ดำ, format 1/2/3, ซ้าย/ขวา | O3: preview เปลี่ยนตาม | P3: MessageCardModal.tsx
A4: TC-CARD-03 | B4: Message Card / Ribbon | C4: Message Card | D4: บรรทัด 1 ว่าง | E4: UI | F4: Validation | G4: High | H4: Not Started | I4: Yes | L4: เปิด modal | M4: TD-03 | N4: เว้นบรรทัด 1 (หรือใส่ space) | O4: ปุ่มบันทึก disable + "กรุณาระบุข้อความบรรทัดที่ 1" | P4: shouldDisableButton
A5: TC-CARD-04 | B5: Message Card / Ribbon | C5: Message Card | D5: บันทึก → card-final | E5: Integration | F5: Positive | G5: High | H5: Not Started | I5: Yes | L5: กรอกบรรทัด 1 | M5: TD-03 | N5: กดบันทึก | O5: ได้ finalId+finalUrl เก็บ messageCardModal-{n}-{code} | P5: card-final.ts
A6: TC-CARD-05 | B6: Message Card / Ribbon | C6: Message Card | D6: หลายพวง validate แยก | E6: Integration | F6: Positive | G6: High | H6: Not Started | I6: Yes | L6: TD-36 (2 พวง) | M6: TD-36 | N6: กรอกป้ายพวงที่ 1 ไม่กรอกพวงที่ 2 → submit checkout | O6: submit disable "กรุณากรอกข้อความป้ายให้ครบทุกพวงหรีด" | P6: validateMessageCards
A7: TC-CARD-06 | B7: Message Card / Ribbon | C7: Message Card | D7: โลโก้ใหญ่เกิน 20x20cm | E7: UI | F7: Validation | G7: Medium | H7: Not Started | I7: Yes | L7: TD-35 รูปใหญ่ | M7: TD-35 | N7: อัปโลโก้ >288px | O7: toast "รูปมีขนาดใหญ่เกินไป กรุณาใช้รูปที่เล็กลง" | P7: MessageCardModal.tsx
A8: TC-CARD-07 | B8: Message Card / Ribbon | C8: Message Card | D8: อัปโหลดล้มเหลว | E8: UI | F8: Negative | G8: Medium | H8: Not Started | I8: Partial | L8: mock media error | M8: TD-24 | N8: อัปโลโก้ตอน API down | O8: toast "...กรุณาลองใหม่อีกครั้ง" | P8: media.ts
A9: TC-CARD-08 | B9: Message Card / Ribbon | C9: Message Card | D9: ไฟล์ไม่ใช่รูป | E9: UI | F9: Negative | G9: Low | H9: Not Started | I9: Yes | L9: TD-35 non-image | M9: TD-35 | N9: เลือก .pdf | O9: accept="image/*" กรอง / BE reject | P9: media.ts
A10: TC-CARD-09 | B10: Message Card / Ribbon | C10: Message Card | D10: ลบโลโก้แล้วอัปใหม่ | E10: UI | F10: Functional | G10: Low | H10: Not Started | I10: Yes | L10: เปิด modal | M10: TD-35 | N10: อัป → ลบ → อัปใหม่ | O10: logoID reset แล้วได้ค่าใหม่ | P10: MessageCardModal.tsx
A11: TC-CARD-10 | B11: Message Card / Ribbon | C11: Message Card | D11: ลบสินค้า → cleanup key | E11: Integration | F11: Session | G11: High | H11: Not Started | I11: Yes | L11: มีป้าย+สินค้า | M11: TD-03 | N11: ลบสินค้าออกจาก cart | O11: messageCardModal-* ถูกล้าง (ไม่รั่วไปออเดอร์ใหม่) | P11: useCart:43-53
A12: TC-CARD-11 | B12: Message Card / Ribbon | C12: Message Card | D12: payload attachments | E12: API | F12: Integration | G12: Medium | H12: Not Started | I12: Yes | L12: กรอกป้ายครบ | M12: TD-03 | N12: submit order | O12: attachments[] มี logo_id/card_id/attached_message_1/2 ถูก | P12: getProductPayload:81-137
A13: TC-CARD-12 | B13: Message Card / Ribbon | C13: Message Card | D13: card-size default | E13: UI | F13: Positive | G13: Low | H13: Not Started | I13: Yes | L13: เปิด MessageCardForWreath | M13: TD-03 | N13: โหลด component | O13: แสดงขนาด/พื้นหลัง default จาก card-size | P13: card-size.ts

Sheet F-ProductDiscovery
A1: Test Case ID | B1: Group | C1: Module | D1: Feature | E1: Test Level | F1: Test Type | G1: Priority | H1: Script Status | I1: Automatable | J1: Assignee | K1: Script File / Notes | L1: Preconditions | M1: Test Data | N1: Test Steps | O1: Expected Result | P1: Code Evidence | Q1: Remark
A2: TC-DISC-01 | B2: Product Discovery | C2: Listing | D2: sort mapping | E2: UI | F2: Functional | G2: Medium | H2: Blocked | I2: Partial | K2: FINDING: เลือก sort แล้ว URL ได้แค่ ?page=1 ไม่มี sort= และลำดับไม่เปลี่ยน — ยืนยันกับ dev | L2: listing | M2: TD-03 | N2: เลือก "แนะนำ" / "ช่วงราคา" | O2: URL/query → recommend / price, ลำดับเปลี่ยน | P2: filter.ts:41-42
A3: TC-DISC-02 | B3: Product Discovery | C3: Listing | D3: filter tag (and/or) | E3: UI | F3: Functional | G3: Medium | H3: Blocked | I3: Partial | K3: filter ไม่ใช่ checkbox มาตรฐาน/ซ่อน + คาดว่าไม่ reflect URL (เทียบ sort) — ต้อง probe ลึก | L3: listing | M3: TD-03 | N3: เลือกหลาย tag | O3: tag_ids_operand and/or ถูกต้อง | P3: StoreController::_products
A4: TC-DISC-03 | B4: Product Discovery | C4: Search | D4: search ?keyword= | E4: UI | F4: Functional | G4: Medium | H4: Blocked | I4: Partial | K4: ?keyword=บุหลัน ไม่กรองผล (15 เท่าเดิม) — ยืนยัน behavior กับ dev | L4: - | M4: TD-03 | N4: เปิด /ร้านพวงหรีด/...?keyword=xxx | O4: กรองตาม keyword (ไม่มีกล่อง UI) | P4: products/page.tsx:62-68
A5: TC-DISC-04 | B5: Product Discovery | C5: Listing | D5: pagination + คง URL | E5: UI | F5: Functional | G5: Medium | H5: Script Done | I5: Yes | K5: tests/discovery/TC-DISC-04_pagination.robot — PASS (15/หน้า, ?page=2) | L5: listing >15 ชิ้น | M5: TD-03 | N5: เปลี่ยนหน้า → refresh | O5: 15/หน้า, state คงใน URL | P5: products/page.tsx
A6: TC-DISC-05 | B6: Product Discovery | C6: Wizard | D6: wizard แนะนำเฉพาะคุณ | E6: UI | F6: Functional | G6: Medium | H6: Script Done | I6: Partial | K6: tests/discovery/TC-DISC-05_wizard-listing-smoke.robot — PASS (smoke; cookie-match รอ TD-37) | L6: TD-37 | M6: TD-37 | N6: เปิด products-special ที่มี cookie | O6: สินค้าตรง key_1..4, load more 20 | P6: products-special/page.tsx
A7: TC-DISC-06 | B7: Product Discovery | C7: Listing | D7: EXCLUDED_TAGS ไม่โผล่ | E7: API | F7: Negative | G7: Medium | H7: Blocked | I7: Partial | K7: ต้องมี slug สินค้าที่ติด EXCLUDED_TAGS ที่ยืนยันแล้ว เพื่อ assert ว่าไม่โผล่ | L7: หมวดมี excluded tag | M7: TD-03 | N7: ดู listing | O7: สินค้า excluded ไม่แสดง | P7: process_excluded_tags
A8: TC-DISC-07 | B8: Product Discovery | C8: Product Detail | D8: allow_add_to_cart=false | E8: UI | F8: Negative | G8: Medium | H8: Blocked | I8: Yes | K8: testdata slug b301-wnw-วลิลา-01-16 ยังมีปุ่มซื้อ (ไม่ใช่ allow_add_to_cart=false) — รอ slug จริง TD-04 | L8: TD-04 | M8: TD-04 | N8: เปิด PDP สินค้าสั่งไม่ได้ | O8: ซ่อน Buy Now + แสดงลิงก์ LINE | P8: ProductButton.tsx:131-150
A9: TC-DISC-08 | B9: Product Discovery | C9: Product Detail | D9: ราคา promotion vs regular | E9: UI | F9: Functional | G9: Medium | H9: Script Done | I9: Yes | K9: tests/discovery/TC-DISC-08_promotion-price.robot — PASS (H014 ราคาตัดทอน ฿1,899) | L9: สินค้ามีโปร | M9: TD-03 | N9: เปิด PDP/listing | O9: แสดงราคาโปร + ราคาตัดทอน | P9: _products promotion
A10: TC-DISC-09 | B10: Product Discovery | C10: Special pages | D10: express/promotion/donate | E10: UI | F10: Smoke | G10: Low | H10: Script Done | I10: Yes | K10: tests/discovery/TC-DISC-09_special-listings-smoke.robot — PASS (express+promotion); donate ตัดออก (finding) | L10: - | N10: เปิด product-express, wreath-promotion, wreath-donate | O10: render, ปุ่ม LINE/pagination ทำงาน | P10: routes
A11: TC-DISC-10 | B11: Product Discovery | C11: Location pages | D11: near-temple/near-me | E11: UI | F11: Smoke | G11: Low | H11: Script Done | I11: Yes | K11: tests/discovery/TC-DISC-10_near-me-smoke.robot — PASS | L11: - | N11: เปิด servicelocation/[slug], wreath-nearme | O11: location selector ตามจังหวัด | P11: routes

Sheet G-Content-SEO
A1: Test Case ID | B1: Group | C1: Module | D1: Feature | E1: Test Level | F1: Test Type | G1: Priority | H1: Script Status | I1: Automatable | J1: Assignee | K1: Script File / Notes | L1: Preconditions | M1: Test Data | N1: Test Steps | O1: Expected Result | P1: Code Evidence | Q1: Remark
A2: TC-CMS-01 | B2: Content / SEO | C2: Article | D2: บทความ listing + filter | E2: UI | F2: Functional | G2: Medium | H2: Blocked | I2: Yes | K2: บทความ listing/filter — รอ article slug จริง (TD-38) | L2: TD-38 | M2: TD-38 | N2: เปิด /บทความ, เลือก category | O2: filter ทำงาน, pagination 20/หน้า | P2: article/page.tsx
A3: TC-CMS-02 | B3: Content / SEO | C3: Article | D3: บทความ detail | E3: UI | F3: Smoke | G3: Low | H3: Blocked | I3: Yes | K3: บทความ detail — รอ slug (TD-38) | L3: TD-38 | M3: TD-38 | N3: เปิด /บทความ/[slug] | O3: render เนื้อหา + JSON-LD BreadcrumbList | P3: article/[slug]
A4: TC-CMS-03 | B4: Content / SEO | C4: Article | D4: ผู้เขียน | E4: UI | F4: Smoke | G4: Low | H4: Blocked | I4: Yes | K4: ผู้เขียน — รอ author slug (TD-38) | L4: TD-38 | M4: TD-38 | N4: เปิด /ผู้เขียน/[slug] | O4: บทความตาม author | P4: author-article/[slug]
A5: TC-CMS-04 | B5: Content / SEO | C5: Service pages | D5: service pages static | E5: UI | F5: Smoke | G5: Low | H5: Script Done | I5: Partial | K5: tests/content/TC-CMS-04_service-pages-smoke.robot — PASS (funeral+all-service); crematory/pet/relics → 404 (finding route ไม่ตรง) | L5: - | N5: เปิด service-funeral/-crematory/-pet/-relics, all-service | O5: 200, มี title/meta/og/canonical, breadcrumb, ข้อมูลติดต่อ | P5: routes
A6: TC-CMS-05 | B6: Content / SEO | C6: Info pages | D6: info pages | E6: UI | F6: Smoke | G6: Low | H6: Script Done | I6: Yes | K6: tests/content/TC-CMS-05_info-pages-smoke.robot — PASS 8 หน้า (title+canonical) | L6: - | N6: เปิด about-us/how-to-order/faqs/privacy/compensation/flower-shop/review-wreath | O6: render + responsive | P6: routes
A7: TC-CMS-06 | B7: Content / SEO | C7: Router | D7: dynamic [...slug] router | E7: UI | F7: Functional | G7: Medium | H7: Not Started | I7: Yes | L7: - | N7: เปิด slug ตาม switch ต่างๆ | O7: route ไปหน้าถูก, Thai URL decode | P7: [...slug]/page.tsx
A8: TC-CMS-07 | B8: Content / SEO | C8: Router | D8: slug มั่ว → 404 | E8: UI | F8: Negative | G8: Medium | H8: Script Done | I8: Yes | K8: tests/content/TC-CMS-07_unknown-slug-404.robot — PASS (เช็ค visible text; NotFound markup ติดมาใน HTML ทุกหน้า) | L8: - | N8: เปิด slug ไม่มีจริง | O8: NotfoundPage (404) | P8: [...slug]/page.tsx
A9: TC-CMS-08 | B9: Content / SEO | C9: Sitemap | D9: sitemap | E9: API | F9: Smoke | G9: Low | H9: Not Started | I9: Yes | L9: - | N9: เปิด /sitemap/* | O9: XML ถูกต้อง | P9: pages/sitemap/*

Sheet H-LINE-B2B
A1: Test Case ID | B1: Group | C1: Module | D1: Feature | E1: Test Level | F1: Test Type | G1: Priority | H1: Script Status | I1: Automatable | J1: Assignee | K1: Script File / Notes | L1: Preconditions | M1: Test Data | N1: Test Steps | O1: Expected Result | P1: Code Evidence | Q1: Remark
A2: TC-LINE-01 | B2: LINE / B2B | C2: LINE | D2: /line set cookie+QR | E2: UI | F2: Functional | G2: Medium | H2: Not Started | I2: Yes | L2: clear cookie | N2: เปิด /line ครั้งแรก | O2: สร้าง UUID, set user_id (30วัน), QR ชี้ /openline/{uuid} | P2: line/page.tsx
A3: TC-LINE-02 | B3: LINE / B2B | C3: LINE | D3: cookie persist | E3: UI | F3: Functional | G3: Low | H3: Not Started | I3: Yes | L3: มี cookie | N3: refresh /line | O3: user_id คงเดิม ไม่สร้างใหม่ | P3: line/page.tsx
A4: TC-LINE-03 | B4: LINE / B2B | C4: OpenLine | D4: openline redirect | E4: UI | F4: Functional | G4: Medium | H4: Not Started | I4: Yes | L4: - | N4: เปิด /openline/{uuid} | O4: set cookie + redirect page.line.me/wreathnawat | P4: openline/[slug]
A5: TC-LINE-04 | B5: LINE / B2B | C5: LINE B2B | D5: b2b แยก cookie/redirect | E5: UI | F5: Functional | G5: Medium | H5: Not Started | I5: Yes | L5: - | N5: เปิด /lineb2b → /openlineb2b/{uuid} | O5: cookie user_id_b2b, redirect @237rjmhp | P5: lineb2b, openlineb2b
A6: TC-LINE-05 | B6: LINE / B2B | C6: LINE Event | D6: event แยก cookie/redirect | E6: UI | F6: Functional | G6: Medium | H6: Not Started | I6: Yes | L6: - | N6: เปิด /line-event → /openline-event/{uuid} | O6: cookie user_id_event, redirect @175ctrfd | P6: line-event, openline-event
A7: TC-LINE-06 | B7: LINE / B2B | C7: LINE | D7: 3 cookie ไม่ชนกัน | E7: UI | F7: Functional | G7: Low | H7: Not Started | I7: Yes | L7: - | N7: เปิดทั้ง 3 flow | O7: user_id/user_id_b2b/user_id_event แยกอิสระ | P7: ทั้ง 3 หน้า

Sheet I-Tracking
A1: Test Case ID | B1: Group | C1: Module | D1: Feature | E1: Test Level | F1: Test Type | G1: Priority | H1: Script Status | I1: Automatable | J1: Assignee | K1: Script File / Notes | L1: Preconditions | M1: Test Data | N1: Test Steps | O1: Expected Result | P1: Code Evidence | Q1: Remark
A2: TC-TRK2-01 | B2: Tracking | C2: Tracking | D2: ค้นด้วย order_code+เบอร์/อีเมล | E2: UI | F2: Positive | G2: Medium | H2: Not Started | I2: Yes | L2: TD-22 | M2: TD-22 | N2: กรอก order_code + phone_or_email → ค้นหา | O2: แสดงสถานะ (path ที่ 2) | P2: tracking/page.tsx:36-44
A3: TC-TRK2-02 | B3: Tracking | C3: Tracking | D3: status 0/1 → notpayment | E3: UI | F3: Functional | G3: Medium | H3: Not Started | I3: Yes | L3: TD-20 | M3: TD-20 | N3: track order ยังไม่จ่าย | O3: แสดง ResultNotpayment | P3: tracking/page.tsx:140-160
A4: TC-TRK2-03 | B4: Tracking | C4: Tracking | D4: status 2/3/4 → result | E4: UI | F4: Functional | G4: Medium | H4: Not Started | I4: Yes | L4: TD-21 | M4: TD-21 | N4: track order จ่ายแล้ว | O4: แสดง Result | P4: tracking/page.tsx:140-160
A5: TC-TRK2-04 | B5: Tracking | C5: Tracking | D5: notFound ไม่ leak | E5: UI | F5: Negative | G5: Medium | H5: Not Started | I5: Yes | L5: - | N5: กรอกข้อมูลผิด | O5: branch notFound, ไม่โชว์ข้อมูลคนอื่น | P5: tracking/page.tsx:55-58
A6: TC-TRK2-05 | B6: Tracking | C6: Tracking | D6: tax invoice module | E6: UI | F6: Functional | G6: Low | H6: Not Started | I6: Partial | L6: flag=y | M6: TD-21 | N6: track order ที่จ่ายแล้ว | O6: fetch hash + แสดงฟอร์มใบกำกับ | P6: NEXT_PUBLIC_ENABLED_TAX_INVOICE_MODULE
A7: TC-TRK2-06 | B7: Tracking | C7: Quotation | D7: quotation flow | E7: UI | F7: Functional | G7: Low | H7: Not Started | I7: Yes | L7: - | N7: เปิด /tracking/quotation | O7: render flow ใบเสนอราคา | P7: tracking/quotation

Sheet J-Contact-Corporate
A1: Test Case ID | B1: Group | C1: Module | D1: Feature | E1: Test Level | F1: Test Type | G1: Priority | H1: Script Status | I1: Automatable | J1: Assignee | K1: Script File / Notes | L1: Preconditions | M1: Test Data | N1: Test Steps | O1: Expected Result | P1: Code Evidence | Q1: Remark
A2: TC-CT-01 | B2: Contact / Corporate | C2: Contact | D2: contact reveal toggle | E2: UI | F2: Functional | G2: Low | H2: Not Started | I2: Yes | L2: - | N2: เปิด /ติดต่อเรา, คลิก LINE/โทร/อีเมล | O2: เผยลิงก์ถูก (line/tel:/mailto:) | P2: contactus/page.tsx
A3: TC-CT-02 | B3: Contact / Corporate | C3: Corporate | D3: corporate FAQ accordion | E3: UI | F3: Functional | G3: Low | H3: Not Started | I3: Yes | L3: - | N3: เปิด /ลูกค้าองค์กร, toggle FAQ 4 ข้อ | O3: เปิด/ปิดถูกต้อง | P3: corporate-customer/page.tsx
A4: TC-CT-03 | B4: Contact / Corporate | C4: Corporate | D4: corporate contact + gallery | E4: UI | F4: Functional | G4: Low | H4: Not Started | I4: Yes | L4: - | N4: คลิก 6 ปุ่ม contact, ดู gallery | O4: ไป /lineb2b/tel/mailto, รูป 20 โหลด | P4: corporate-customer/page.tsx

Sheet K-Global
A1: Test Case ID | B1: Group | C1: Module | D1: Feature | E1: Test Level | F1: Test Type | G1: Priority | H1: Script Status | I1: Automatable | J1: Assignee | K1: Script File / Notes | L1: Preconditions | M1: Test Data | N1: Test Steps | O1: Expected Result | P1: Code Evidence | Q1: Remark
A2: TC-GBL-01 | B2: Global Components | C2: Header | D2: announcement bar | E2: UI | F2: Functional | G2: Low | H2: Skipped | I2: Partial | K2: announcement bar = strip "ส่งฟรีทั่ว กทม." แสดงได้ แต่ปุ่มปิดผูกกับ cookie × คลุมเครือ — เลื่อนไว้ | L2: มี announcement active | N2: โหลดทุกหน้า | O2: bar แสดงข้อความ + ปิดได้ | P2: AnnouncementBar.tsx
A3: TC-GBL-02 | B3: Global Components | C3: Header | D3: mini-cart badge+dropdown | E3: UI | F3: Functional | G3: Medium | H3: Script Done | I3: Partial | K3: tests/global/TC-GBL-02_minicart-badge.robot — PASS (badge=1; dropdown ไม่ assert) | L3: มีของในตะกร้า | M3: TD-03 | N3: คลิกไอคอนตะกร้า | O3: badge จำนวนถูก, dropdown รายการ | P3: ShoppingCart.tsx
A4: TC-GBL-03 | B4: Global Components | C4: Footer | D4: floating contact / sticky bar | E4: UI | F4: Functional | G4: Low | H4: Skipped | I4: Partial | K4: floating contact/sticky (mobile) — hook อ่อน ต้อง probe viewport เพิ่ม | L4: mobile | N4: เลื่อนหน้า | O4: FloatingContactButton + StickyBars แสดง/คลิกได้ | P4: Footer/*
A5: TC-GBL-04 | B5: Global Components | C5: Footer | D5: back to top | E5: UI | F5: Functional | G5: Low | H5: Script Done | I5: Yes | K5: tests/global/TC-GBL-04_back-to-top.robot — PASS (ปุ่ม fixed bottom-20) | L5: หน้ายาว | N5: เลื่อนลง → คลิก | O5: scroll กลับบนสุด | P5: BackToTop.tsx
A6: TC-GBL-05 | B6: Global Components | C6: Header | D6: responsive nav (hamburger) | E6: UI | F6: Functional | G6: Medium | H6: Skipped | I6: Partial | K6: hamburger/MobileNavBar — ยังไม่เจอ selector ชัด (ไม่มี aria/class ตรง) ต้อง probe เพิ่ม | L6: mobile viewport | N6: เปิดเมนูมือถือ | O6: MobileNavBar เปิด/นำทางถูก | P6: MobileNavBar.tsx

Sheet L-Cross-cutting
A1: Test Case ID | B1: Group | C1: Module | D1: Feature | E1: Test Level | F1: Test Type | G1: Priority | H1: Script Status | I1: Automatable | J1: Assignee | K1: Script File / Notes | L1: Preconditions | M1: Test Data | N1: Test Steps | O1: Expected Result | P1: Code Evidence | Q1: Remark
A2: TC-XAPI-01 | B2: Cross-cutting | C2: API Error | D2: ERP 422 → modal | E2: API/UI | F2: Negative | G2: High | H2: Not Started | I2: Partial | L2: mock 422 | M2: TD-24 | N2: submit order/total | O2: proxy {error:true} → openErrorModal ไม่ crash | P2: pages/api/order.ts catch
A3: TC-XAPI-02 | B3: Cross-cutting | C3: API Error | D3: ERP 500/timeout | E3: API/UI | F3: Negative | G3: High | H3: Not Started | I3: Partial | L3: mock 500/delay | M3: TD-24 | N3: เรียก total-payment/order | O3: modal error, ไม่ค้าง/crash | P3: instance.ts interceptors
A4: TC-XSESS-01 | B4: Cross-cutting | C4: Session | D4: 401 → clear+reload | E4: UI | F4: Session | G4: High | H4: Not Started | I4: Partial | L4: login + mock 401 | M4: TD-24 | N4: เรียก ERP_API ระหว่าง flow | O4: clearStorage() + reload | P4: instance.ts ERP_API
A5: TC-XSESS-02 | B5: Cross-cutting | C5: Session | D5: token หมดอายุกลาง flow | E5: UI | F5: Session | G5: Medium | H5: Not Started | I5: Partial | L5: token หมดอายุ | M5: TD-02 | N5: กระทำต่อ | O5: จัดการ session หมด ไม่ค้าง | P5: instance.ts
A6: TC-XSEC-01 | B6: Cross-cutting | C6: Security | D6: consent bypass (PDPA) | E6: API | F6: Security | G6: High | H6: Not Started | I6: Yes | L6: - | N6: POST /api/order ไม่มี privacy_policy | O6: DEF-L1: BE ไม่ block → flag ความเสี่ยง + แจ้ง dev | P6: OrderController::store | Q6: DEF-L1
A7: TC-XSEC-02 | B7: Cross-cutting | C7: Security | D7: phone FE≠BE | E7: API | F7: Security | G7: Medium | H7: Not Started | I7: Yes | L7: - | N7: ส่ง +66.../มี space ตรง API | O7: DEF-L2: FE reject แต่ BE รับ → flag inconsistency | P7: validation.ts vs OrderController | Q7: DEF-L2
A8: TC-XSEC-03 | B8: Cross-cutting | C8: Security | D8: line_id regex | E8: UI | F8: Validation | G8: Low | H8: Not Started | I8: Yes | L8: checkout | M8: TD-03 | N8: line_id อักษรใหญ่/>20 | O8: FE reject ตาม ^[a-z0-9_-]{,20}$ | P8: validation.ts:27-33
A9: TC-XSEC-04 | B9: Cross-cutting | C9: Security | D9: XSS/SQLi ในป้าย/ศาลา | E9: API | F9: Security | G9: Medium | H9: Not Started | I9: Partial | L9: - | N9: กรอก <script> / ' OR '1'='1 | O9: ไม่ execute/ไม่ 500 (Eloquent param) | P9: OrderController::store
A10: TC-XPERF-01 | B10: Cross-cutting | C10: Race | D10: double-submit ชำระ | E10: UI | F10: Race | G10: High | H10: Not Started | I10: Yes | L10: กรอก checkout ครบ | M10: TD-03 | N10: กดชำระรัว 2 ครั้ง | O10: isSubmitting block ครั้งที่ 2, ไม่สร้างออเดอร์ซ้ำ | P10: CheckoutForm:onSubmit
A11: TC-XPERF-02 | B11: Cross-cutting | C11: SEO | D11: SEO/JSON-LD/canonical | E11: UI | F11: Functional | G11: Low | H11: Not Started | I11: Partial | L11: - | N11: ตรวจ meta/og/JSON-LD หน้า PDP/article | O11: structured data ครบ, canonical ถูก | P11: page metadata
A12: TC-XPERF-03 | B12: Cross-cutting | C12: Compat | D12: responsive/cross-browser | E12: UI | F12: Compat | G12: Low | H12: Not Started | I12: Manual | L12: - | N12: ทดสอบ datepicker/upload/clipboard บนมือถือ | O12: ทำงานข้าม browser/อุปกรณ์ | P12: ทั่วไป

Sheet summary_fullsite
A1: Full-Site Test Cases — Summary (แยกชีตตามประเภท)
A3: Total test cases | B3: 113
A5: Script Status | B5: Count (live)
A6: Not Started | B6: =COUNTIF('A-Account-Auth'!H:H,"Not Started")+COUNTIF('B-MessageCard'!H:H,"Not Started")+COUNTIF('F-ProductDiscovery'!H:H,"Not Started")+COUNTIF('G-Content-SEO'!H:H,"Not Started")+COUNTIF('H-LINE-B2B'!H:H,"Not Started")+COUNTIF('I-Tracking'!H:H,"Not Started")+COUNTIF('J-Contact-Corporate'!H:H,"Not Started")+COUNTIF('K-Global'!H:H,"Not Started")+COUNTIF('L-Cross-cutting'!H:H,"Not Started")
A7: In Progress | B7: =COUNTIF('A-Account-Auth'!H:H,"In Progress")+COUNTIF('B-MessageCard'!H:H,"In Progress")+COUNTIF('F-ProductDiscovery'!H:H,"In Progress")+COUNTIF('G-Content-SEO'!H:H,"In Progress")+COUNTIF('H-LINE-B2B'!H:H,"In Progress")+COUNTIF('I-Tracking'!H:H,"In Progress")+COUNTIF('J-Contact-Corporate'!H:H,"In Progress")+COUNTIF('K-Global'!H:H,"In Progress")+COUNTIF('L-Cross-cutting'!H:H,"In Progress")
A8: Script Done | B8: =COUNTIF('A-Account-Auth'!H:H,"Script Done")+COUNTIF('B-MessageCard'!H:H,"Script Done")+COUNTIF('F-ProductDiscovery'!H:H,"Script Done")+COUNTIF('G-Content-SEO'!H:H,"Script Done")+COUNTIF('H-LINE-B2B'!H:H,"Script Done")+COUNTIF('I-Tracking'!H:H,"Script Done")+COUNTIF('J-Contact-Corporate'!H:H,"Script Done")+COUNTIF('K-Global'!H:H,"Script Done")+COUNTIF('L-Cross-cutting'!H:H,"Script Done")
A9: Reviewed | B9: =COUNTIF('A-Account-Auth'!H:H,"Reviewed")+COUNTIF('B-MessageCard'!H:H,"Reviewed")+COUNTIF('F-ProductDiscovery'!H:H,"Reviewed")+COUNTIF('G-Content-SEO'!H:H,"Reviewed")+COUNTIF('H-LINE-B2B'!H:H,"Reviewed")+COUNTIF('I-Tracking'!H:H,"Reviewed")+COUNTIF('J-Contact-Corporate'!H:H,"Reviewed")+COUNTIF('K-Global'!H:H,"Reviewed")+COUNTIF('L-Cross-cutting'!H:H,"Reviewed")
A10: Blocked | B10: =COUNTIF('A-Account-Auth'!H:H,"Blocked")+COUNTIF('B-MessageCard'!H:H,"Blocked")+COUNTIF('F-ProductDiscovery'!H:H,"Blocked")+COUNTIF('G-Content-SEO'!H:H,"Blocked")+COUNTIF('H-LINE-B2B'!H:H,"Blocked")+COUNTIF('I-Tracking'!H:H,"Blocked")+COUNTIF('J-Contact-Corporate'!H:H,"Blocked")+COUNTIF('K-Global'!H:H,"Blocked")+COUNTIF('L-Cross-cutting'!H:H,"Blocked")
A11: Skipped | B11: =COUNTIF('A-Account-Auth'!H:H,"Skipped")+COUNTIF('B-MessageCard'!H:H,"Skipped")+COUNTIF('F-ProductDiscovery'!H:H,"Skipped")+COUNTIF('G-Content-SEO'!H:H,"Skipped")+COUNTIF('H-LINE-B2B'!H:H,"Skipped")+COUNTIF('I-Tracking'!H:H,"Skipped")+COUNTIF('J-Contact-Corporate'!H:H,"Skipped")+COUNTIF('K-Global'!H:H,"Skipped")+COUNTIF('L-Cross-cutting'!H:H,"Skipped")
A13: By Priority | B13: Count
A14: High | B14: =COUNTIF('A-Account-Auth'!G:G,"High*")+COUNTIF('B-MessageCard'!G:G,"High*")+COUNTIF('F-ProductDiscovery'!G:G,"High*")+COUNTIF('G-Content-SEO'!G:G,"High*")+COUNTIF('H-LINE-B2B'!G:G,"High*")+COUNTIF('I-Tracking'!G:G,"High*")+COUNTIF('J-Contact-Corporate'!G:G,"High*")+COUNTIF('K-Global'!G:G,"High*")+COUNTIF('L-Cross-cutting'!G:G,"High*")
A15: Medium | B15: =COUNTIF('A-Account-Auth'!G:G,"Medium*")+COUNTIF('B-MessageCard'!G:G,"Medium*")+COUNTIF('F-ProductDiscovery'!G:G,"Medium*")+COUNTIF('G-Content-SEO'!G:G,"Medium*")+COUNTIF('H-LINE-B2B'!G:G,"Medium*")+COUNTIF('I-Tracking'!G:G,"Medium*")+COUNTIF('J-Contact-Corporate'!G:G,"Medium*")+COUNTIF('K-Global'!G:G,"Medium*")+COUNTIF('L-Cross-cutting'!G:G,"Medium*")
A16: Low | B16: =COUNTIF('A-Account-Auth'!G:G,"Low*")+COUNTIF('B-MessageCard'!G:G,"Low*")+COUNTIF('F-ProductDiscovery'!G:G,"Low*")+COUNTIF('G-Content-SEO'!G:G,"Low*")+COUNTIF('H-LINE-B2B'!G:G,"Low*")+COUNTIF('I-Tracking'!G:G,"Low*")+COUNTIF('J-Contact-Corporate'!G:G,"Low*")+COUNTIF('K-Global'!G:G,"Low*")+COUNTIF('L-Cross-cutting'!G:G,"Low*")
A18: By Sheet (ประเภท) | B18: Count
A19: A-Account-Auth (Account / Auth) | B19: =COUNTA('A-Account-Auth'!A:A)-1
A20: B-MessageCard (Message Card / Ribbon) | B20: =COUNTA('B-MessageCard'!A:A)-1
A21: F-ProductDiscovery (Product Discovery) | B21: =COUNTA('F-ProductDiscovery'!A:A)-1
A22: G-Content-SEO (Content / SEO) | B22: =COUNTA('G-Content-SEO'!A:A)-1
A23: H-LINE-B2B (LINE / B2B) | B23: =COUNTA('H-LINE-B2B'!A:A)-1
A24: I-Tracking (Tracking) | B24: =COUNTA('I-Tracking'!A:A)-1
A25: J-Contact-Corporate (Contact / Corporate) | B25: =COUNTA('J-Contact-Corporate'!A:A)-1
A26: K-Global (Global Components) | B26: =COUNTA('K-Global'!A:A)-1
A27: L-Cross-cutting (Cross-cutting) | B27: =COUNTA('L-Cross-cutting'!A:A)-1
A29: By Automatable | B29: Count
A30: Yes | B30: =COUNTIF('A-Account-Auth'!I:I,"Yes")+COUNTIF('B-MessageCard'!I:I,"Yes")+COUNTIF('F-ProductDiscovery'!I:I,"Yes")+COUNTIF('G-Content-SEO'!I:I,"Yes")+COUNTIF('H-LINE-B2B'!I:I,"Yes")+COUNTIF('I-Tracking'!I:I,"Yes")+COUNTIF('J-Contact-Corporate'!I:I,"Yes")+COUNTIF('K-Global'!I:I,"Yes")+COUNTIF('L-Cross-cutting'!I:I,"Yes")
A31: Partial | B31: =COUNTIF('A-Account-Auth'!I:I,"Partial")+COUNTIF('B-MessageCard'!I:I,"Partial")+COUNTIF('F-ProductDiscovery'!I:I,"Partial")+COUNTIF('G-Content-SEO'!I:I,"Partial")+COUNTIF('H-LINE-B2B'!I:I,"Partial")+COUNTIF('I-Tracking'!I:I,"Partial")+COUNTIF('J-Contact-Corporate'!I:I,"Partial")+COUNTIF('K-Global'!I:I,"Partial")+COUNTIF('L-Cross-cutting'!I:I,"Partial")
A32: Manual | B32: =COUNTIF('A-Account-Auth'!I:I,"Manual")+COUNTIF('B-MessageCard'!I:I,"Manual")+COUNTIF('F-ProductDiscovery'!I:I,"Manual")+COUNTIF('G-Content-SEO'!I:I,"Manual")+COUNTIF('H-LINE-B2B'!I:I,"Manual")+COUNTIF('I-Tracking'!I:I,"Manual")+COUNTIF('J-Contact-Corporate'!I:I,"Manual")+COUNTIF('K-Global'!I:I,"Manual")+COUNTIF('L-Cross-cutting'!I:I,"Manual")

Sheet Progress 2026-06-30
A1: สรุปความคืบหน้า Automation | B1: 2026-06-30 (Claude Code session)
A3: ทำเสร็จ + รันผ่านบน staging | B3: 25 เคส (+ Content/SEO: CMS-04 service, CMS-05 info×8, CMS-07 404)
A4: Coupon (tests/promo/) | B4: TC-PROMO-04 guest / 02-R invalid / 03-R empty / 07 used
A5: Checkout rules | B5: TC-CHK-09 วันอดีต / TC-CHK-11 >30วัน boundary / TC-CHK-13 ป้าย<จำนวนพวง
A6: User-infos (A6) | B6: TC-USER-01 guest / 02 prefill / 05 email RO / 12 logout / 13 tab switch ; TC-OH-02 empty orders
A8: Blocked รอ data/วิธี | B8: 8 เคส
A9: รอ coupon data จาก dev | B9: TC-PROMO-01-R / 05 / 06 / 09 / 10 (ดู QA-Coupon-TestData-Request.md)
A10: รอ codeExpired จริง | B10: TC-PROMO-02-R (sub-case expired) — WD12 ไม่ reject
A11: ต้องเปิด API track | B11: TC-CHK-12 slug ปลอม (POST /api/order) — รอ RequestsLibrary
A12: flaky ตามเวลา | B12: TC-CHK-10 จัดส่ง <4ชม. — รอ mock เวลา
A14: แก้ infra ระหว่างทาง | B14: - Fix bug Click First Visible (auth) ที่ทำ login พังทั้งชุด
B15: - เพิ่ม helper first-visible input/click + retry กัน stale element
B16: - เพิ่ม keyword ปฏิทินจัดส่ง (boundary) + coupon apply/error
B17: - เพิ่ม date helper relative_aria_label / aria_date_part
B18: - coupons.json ใส่ code staging จริง; route USER_INFOS
A20: คำสั่งรัน | B20: robot --listener listeners/ScreenshotListener.py \
B21: --pythonpath libraries --pythonpath . \
B22: --variablefile resources/variables/env_staging.yaml \
B23: --exclude createsorder --outputdir results tests
A25: git | B25: branch qa/coupon-checkout-rules-user-infos, commit 838395e
A26: หมายเหตุ ID ซ้ำ | B26: repo file checkout/TC-CHK-09_out-of-province ใช้ ID ผิด (ที่จริง=TC-CART-05-R)

Sheet summary
A1: Script Status Tracker — Summary
A3: Total test cases | B3: 75
A5: Script Status | B5: Count (live)
A6: Not Started | B6: =COUNTIF(checkout!H:H,"Not Started")
A7: In Progress | B7: =COUNTIF(checkout!H:H,"In Progress")
A8: Script Done | B8: =COUNTIF(checkout!H:H,"Script Done")
A9: Reviewed | B9: =COUNTIF(checkout!H:H,"Reviewed")
A10: Blocked | B10: =COUNTIF(checkout!H:H,"Blocked")
A11: Skipped | B11: =COUNTIF(checkout!H:H,"Skipped")
A13: By Priority | B13: Count
A14: High | B14: =COUNTIF(checkout!G:G,"High*")
A15: Medium | B15: =COUNTIF(checkout!G:G,"Medium*")
A16: Low | B16: =COUNTIF(checkout!G:G,"Low*")
A18: By Group | B18: Count
A19: Home / Navigation | B19: =COUNTIF(checkout!B:B,"Home / Navigation")
A20: Category / Listing / Search | B20: =COUNTIF(checkout!B:B,"Category / Listing / Search")
A21: Product Detail | B21: =COUNTIF(checkout!B:B,"Product Detail")
A22: Cart | B22: =COUNTIF(checkout!B:B,"Cart")
A23: Checkout (Validation + Shipping + Message Card) | B23: =COUNTIF(checkout!B:B,"Checkout (Validation + Shipping + Message Card)")
A24: Coupon / Promotion | B24: =COUNTIF(checkout!B:B,"Coupon / Promotion")
A25: Register / Auth (during checkout) | B25: =COUNTIF(checkout!B:B,"Register / Auth (during checkout)")
A26: Payment | B26: =COUNTIF(checkout!B:B,"Payment")
A27: Order Success / Tracking | B27: =COUNTIF(checkout!B:B,"Order Success / Tracking")
A28: Cross-cutting: API Error / Session / Security / Responsive | B28: =COUNTIF(checkout!B:B,"Cross-cutting: API Error / Session / Security / Responsive")
